<?xml version="1.0" encoding="utf-8"?><index><stem n="моя"><phr n="Моя"><ent r="7" t="82" w="123" /><ent r="7" t="82" w="123" /><ent r="3" t="84" w="57" /><ent r="3" t="84" w="57" /><ent r="3" t="289" w="55" /><ent r="3" t="289" w="55" /><ent r="5" t="327" w="186" /><ent r="5" t="327" w="186" /><ent r="100" t="397" w="37" /><ent r="100" t="397" w="37" /><ent r="5" t="397" w="300" /><ent r="5" t="397" w="300" /></phr></stem><stem n="содержимое"><phr n="содержимое"><ent r="7" t="82" w="133" /><ent r="7" t="82" w="133" /><ent r="7" t="82" w="140" /><ent r="7" t="82" w="140" /><ent r="6" t="84" w="294" /><ent r="6" t="84" w="294" /><ent r="6" t="84" w="333" /><ent r="6" t="84" w="333" /><ent r="64" t="84" w="613" /><ent r="64" t="84" w="613" /><ent r="5" t="85" w="370" /><ent r="5" t="85" w="370" /><ent r="6" t="85" w="510" /><ent r="6" t="85" w="510" /><ent r="3" t="145" w="119" /><ent r="3" t="145" w="119" /><ent r="6" t="404" w="95" /><ent r="6" t="404" w="95" /><ent r="8" t="505" w="735" /><ent r="8" t="505" w="735" /><ent r="6" t="579" w="451" /><ent r="6" t="579" w="451" /><ent r="6" t="579" w="461" /><ent r="6" t="579" w="461" /><ent r="3" t="611" w="29" /><ent r="3" t="611" w="29" /><ent r="4" t="678" w="85" /><ent r="4" t="679" w="89" /></phr><phr n="Содержимое"><ent r="7" t="194" w="255" /><ent r="7" t="194" w="255" /></phr></stem><stem n="виджете"><phr n="виджете"><ent r="6" t="82" w="148" /><ent r="6" t="82" w="2129" /><ent r="6" t="82" w="2208" /><ent r="6" t="82" w="2208" /><ent r="3" t="85" w="35" /><ent r="3" t="85" w="35" /><ent r="4" t="85" w="1082" /><ent r="4" t="85" w="1082" /><ent r="4" t="360" w="124" /><ent r="4" t="360" w="124" /></phr></stem><stem n="круговой"><phr n="круговой"><ent r="57" t="82" w="157" /><ent r="57" t="82" w="157" /><ent r="3" t="83" w="99" /><ent r="3" t="83" w="99" /><ent r="4" t="85" w="666" /><ent r="4" t="85" w="666" /></phr><phr n="Круговой"><ent r="57" t="82" w="162" /><ent r="57" t="82" w="162" /></phr></stem><stem n="диаграммы"><phr n="диаграммы"><ent r="57" t="82" w="158" /><ent r="3" t="83" w="102" /><ent r="3" t="84" w="124" /><ent r="3" t="84" w="124" /><ent r="4" t="85" w="212" /><ent r="4" t="85" w="667" /><ent r="4" t="85" w="667" /></phr></stem><stem n="диаграммой"><phr n="диаграммой"><ent r="57" t="82" w="163" /></phr></stem><stem n="пустой"><phr n="Пустой"><ent r="57" t="82" w="165" /><ent r="57" t="82" w="165" /></phr></stem><stem n="отобразится"><phr n="отобразится"><ent r="57" t="82" w="167" /><ent r="57" t="82" w="167" /><ent r="6" t="82" w="211" /><ent r="6" t="82" w="211" /><ent r="11" t="82" w="237" /><ent r="11" t="82" w="237" /><ent r="11" t="82" w="247" /><ent r="11" t="82" w="247" /><ent r="11" t="82" w="490" /><ent r="11" t="82" w="490" /><ent r="11" t="82" w="500" /><ent r="11" t="82" w="500" /><ent r="11" t="82" w="757" /><ent r="11" t="82" w="757" /><ent r="11" t="82" w="767" /><ent r="11" t="82" w="767" /><ent r="11" t="82" w="1023" /><ent r="11" t="82" w="1023" /><ent r="11" t="82" w="1219" /><ent r="11" t="82" w="1219" /><ent r="11" t="82" w="1229" /><ent r="11" t="82" w="1229" /><ent r="6" t="84" w="398" /><ent r="6" t="84" w="398" /><ent r="3" t="114" w="53" /><ent r="3" t="114" w="53" /><ent r="8" t="147" w="365" /><ent r="8" t="147" w="365" /><ent r="8" t="147" w="780" /><ent r="8" t="147" w="780" /><ent r="6" t="153" w="150" /><ent r="6" t="153" w="150" /><ent r="6" t="154" w="166" /><ent r="4" t="174" w="59" /><ent r="4" t="174" w="59" /><ent r="6" t="211" w="118" /><ent r="6" t="211" w="118" /><ent r="6" t="213" w="140" /><ent r="6" t="213" w="140" /><ent r="6" t="216" w="123" /><ent r="6" t="216" w="123" /><ent r="6" t="219" w="88" /><ent r="6" t="219" w="88" /><ent r="6" t="220" w="120" /><ent r="6" t="220" w="120" /><ent r="6" t="222" w="118" /><ent r="6" t="222" w="118" /><ent r="3" t="224" w="212" /><ent r="3" t="224" w="212" /><ent r="6" t="225" w="107" /><ent r="6" t="225" w="107" /><ent r="6" t="230" w="233" /><ent r="6" t="230" w="233" /><ent r="5" t="332" w="357" /><ent r="5" t="332" w="357" /><ent r="6" t="334" w="126" /><ent r="6" t="334" w="126" /><ent r="5" t="442" w="136" /><ent r="5" t="442" w="136" /><ent r="3" t="501" w="179" /><ent r="3" t="501" w="179" /><ent r="4" t="706" w="291" /><ent r="4" t="706" w="291" /><ent r="8" t="708" w="136" /><ent r="8" t="708" w="136" /><ent r="5" t="710" w="110" /><ent r="5" t="710" w="110" /></phr><phr n="Отобразится"><ent r="5" t="140" w="221" /><ent r="5" t="140" w="221" /><ent r="6" t="220" w="56" /><ent r="6" t="220" w="56" /><ent r="3" t="308" w="59" /><ent r="3" t="308" w="59" /><ent r="4" t="426" w="70" /><ent r="4" t="426" w="70" /><ent r="4" t="686" w="108" /><ent r="4" t="686" w="108" /></phr></stem><stem n="редактор"><phr n="редактор"><ent r="57" t="82" w="173" /><ent r="57" t="82" w="173" /><ent r="6" t="82" w="1882" /><ent r="6" t="410" w="136" /><ent r="6" t="410" w="136" /><ent r="4" t="676" w="229" /><ent r="4" t="676" w="229" /><ent r="3" t="678" w="13" /><ent r="3" t="678" w="13" /><ent r="4" t="678" w="148" /><ent r="55" t="678" w="188" /><ent r="55" t="678" w="188" /><ent r="6" t="683" w="67" /><ent r="6" t="683" w="158" /><ent r="6" t="683" w="158" /><ent r="100" t="697" w="7" /><ent r="100" t="697" w="7" /><ent r="100" t="697" w="13" /><ent r="100" t="697" w="13" /><ent r="6" t="697" w="158" /><ent r="6" t="697" w="158" /><ent r="100" t="698" w="6" /><ent r="100" t="698" w="6" /><ent r="100" t="698" w="9" /><ent r="100" t="698" w="9" /><ent r="100" t="698" w="14" /><ent r="100" t="698" w="14" /><ent r="6" t="698" w="135" /><ent r="6" t="698" w="135" /><ent r="100" t="699" w="6" /><ent r="100" t="699" w="6" /><ent r="100" t="699" w="11" /><ent r="100" t="699" w="11" /><ent r="6" t="699" w="132" /><ent r="6" t="699" w="132" /><ent r="3" t="700" w="103" /><ent r="3" t="700" w="103" /><ent r="3" t="700" w="133" /><ent r="3" t="700" w="133" /><ent r="4" t="700" w="297" /><ent r="4" t="700" w="297" /></phr><phr n="Редактор"><ent r="5" t="145" w="167" /><ent r="5" t="145" w="167" /><ent r="5" t="148" w="291" /><ent r="5" t="148" w="291" /><ent r="5" t="148" w="301" /><ent r="5" t="148" w="301" /><ent r="5" t="149" w="299" /><ent r="5" t="149" w="299" /><ent r="7" t="498" w="162" /><ent r="7" t="498" w="162" /><ent r="7" t="498" w="239" /><ent r="7" t="498" w="239" /><ent r="8" t="505" w="774" /><ent r="8" t="505" w="774" /><ent r="65" t="676" w="83" /><ent r="65" t="676" w="83" /><ent r="65" t="676" w="173" /><ent r="65" t="676" w="173" /><ent r="6" t="679" w="183" /><ent r="6" t="679" w="183" /><ent r="4" t="680" w="69" /><ent r="4" t="680" w="69" /><ent r="65" t="682" w="50" /><ent r="65" t="682" w="50" /><ent r="4" t="682" w="65" /><ent r="4" t="682" w="65" /><ent r="4" t="682" w="99" /><ent r="4" t="682" w="99" /><ent r="3" t="685" w="36" /><ent r="3" t="685" w="36" /><ent r="65" t="685" w="88" /><ent r="65" t="685" w="88" /><ent r="4" t="685" w="101" /><ent r="4" t="685" w="101" /><ent r="3" t="687" w="26" /><ent r="3" t="687" w="26" /><ent r="3" t="688" w="32" /><ent r="3" t="688" w="32" /><ent r="65" t="689" w="106" /><ent r="65" t="689" w="106" /><ent r="65" t="690" w="67" /><ent r="65" t="690" w="67" /><ent r="5" t="690" w="201" /><ent r="5" t="690" w="201" /><ent r="3" t="697" w="45" /><ent r="3" t="697" w="45" /><ent r="3" t="697" w="66" /><ent r="3" t="697" w="66" /><ent r="67" t="697" w="314" /><ent r="67" t="697" w="314" /><ent r="3" t="698" w="42" /><ent r="3" t="698" w="42" /><ent r="3" t="698" w="63" /><ent r="3" t="698" w="63" /><ent r="67" t="698" w="246" /><ent r="67" t="698" w="246" /><ent r="3" t="699" w="39" /><ent r="3" t="699" w="39" /><ent r="3" t="699" w="60" /><ent r="3" t="699" w="60" /><ent r="67" t="699" w="218" /><ent r="67" t="699" w="218" /><ent r="3" t="700" w="41" /><ent r="3" t="700" w="41" /></phr></stem><stem n="произведите"><phr n="Произведите"><ent r="6" t="82" w="201" /><ent r="6" t="82" w="201" /></phr><phr n="произведите"><ent r="7" t="110" w="193" /><ent r="7" t="110" w="193" /><ent r="6" t="142" w="331" /><ent r="6" t="142" w="331" /><ent r="6" t="142" w="380" /><ent r="6" t="142" w="380" /><ent r="6" t="143" w="554" /><ent r="6" t="143" w="554" /><ent r="6" t="143" w="636" /><ent r="6" t="143" w="636" /><ent r="6" t="521" w="138" /><ent r="6" t="521" w="138" /><ent r="7" t="526" w="103" /><ent r="7" t="526" w="103" /><ent r="6" t="541" w="262" /><ent r="6" t="541" w="262" /></phr></stem><stem n="изменениями"><phr n="изменениями"><ent r="6" t="82" w="213" /><ent r="5" t="162" w="297" /><ent r="6" t="651" w="145" /><ent r="6" t="651" w="236" /></phr></stem><stem n="графический"><phr n="графический"><ent r="5" t="82" w="216" /><ent r="5" t="82" w="216" /></phr></stem><stem n="гистограмма"><phr n="Гистограмма"><ent r="10" t="82" w="231" /><ent r="10" t="82" w="231" /><ent r="100" t="85" w="202" /><ent r="100" t="85" w="202" /><ent r="5" t="85" w="204" /><ent r="5" t="85" w="204" /></phr></stem><stem n="подпись"><phr n="Подпись"><ent r="12" t="82" w="243" /><ent r="12" t="82" w="243" /><ent r="12" t="82" w="496" /><ent r="12" t="82" w="496" /><ent r="12" t="82" w="763" /><ent r="12" t="82" w="763" /><ent r="12" t="82" w="1225" /><ent r="12" t="82" w="1225" /><ent r="8" t="679" w="252" /><ent r="8" t="679" w="252" /></phr><phr n="подпись"><ent r="6" t="147" w="702" /><ent r="6" t="147" w="702" /><ent r="6" t="185" w="268" /><ent r="6" t="185" w="268" /><ent r="4" t="384" w="34" /><ent r="6" t="685" w="148" /><ent r="6" t="685" w="148" /></phr></stem><stem n="сущность"><phr n="Сущность"><ent r="12" t="82" w="255" /><ent r="12" t="82" w="255" /><ent r="11" t="82" w="257" /><ent r="11" t="82" w="257" /><ent r="12" t="82" w="508" /><ent r="12" t="82" w="508" /><ent r="11" t="82" w="510" /><ent r="11" t="82" w="510" /><ent r="12" t="82" w="775" /><ent r="12" t="82" w="775" /><ent r="11" t="82" w="777" /><ent r="11" t="82" w="777" /><ent r="12" t="82" w="1029" /><ent r="12" t="82" w="1029" /><ent r="11" t="82" w="1031" /><ent r="11" t="82" w="1031" /><ent r="12" t="82" w="1237" /><ent r="12" t="82" w="1237" /><ent r="11" t="82" w="1239" /><ent r="11" t="82" w="1239" /><ent r="7" t="82" w="1512" /><ent r="7" t="82" w="1512" /><ent r="5" t="85" w="401" /><ent r="5" t="85" w="401" /><ent r="6" t="85" w="540" /><ent r="6" t="85" w="540" /><ent r="3" t="99" w="26" /><ent r="3" t="99" w="26" /><ent r="3" t="233" w="193" /><ent r="6" t="513" w="155" /><ent r="6" t="513" w="163" /><ent r="5" t="597" w="202" /><ent r="5" t="597" w="202" /></phr><phr n="сущность"><ent r="8" t="82" w="1936" /><ent r="8" t="82" w="1936" /><ent r="7" t="448" w="91" /><ent r="7" t="448" w="91" /><ent r="4" t="512" w="94" /><ent r="4" t="530" w="147" /><ent r="5" t="531" w="79" /><ent r="5" t="531" w="79" /><ent r="4" t="531" w="94" /><ent r="5" t="531" w="146" /><ent r="5" t="531" w="146" /><ent r="4" t="540" w="247" /></phr></stem><stem n="графиков"><phr n="графиков"><ent r="11" t="82" w="278" /><ent r="11" t="82" w="278" /><ent r="11" t="82" w="531" /><ent r="11" t="82" w="531" /><ent r="11" t="82" w="798" /><ent r="11" t="82" w="798" /><ent r="11" t="82" w="1052" /><ent r="11" t="82" w="1052" /><ent r="11" t="82" w="1260" /><ent r="11" t="82" w="1260" /></phr></stem><stem n="списков"><phr n="списков"><ent r="11" t="82" w="280" /><ent r="11" t="82" w="533" /><ent r="11" t="82" w="800" /><ent r="11" t="82" w="1054" /><ent r="11" t="82" w="1262" /><ent r="6" t="82" w="1520" /><ent r="3" t="130" w="27" /><ent r="3" t="130" w="27" /><ent r="9" t="382" w="141" /><ent r="3" t="389" w="71" /><ent r="3" t="389" w="71" /><ent r="64" t="468" w="36" /><ent r="64" t="468" w="36" /><ent r="7" t="630" w="83" /><ent r="7" t="630" w="83" /><ent r="7" t="704" w="139" /><ent r="7" t="704" w="139" /></phr></stem><stem n="использованы"><phr n="использованы"><ent r="11" t="82" w="302" /><ent r="11" t="82" w="302" /><ent r="11" t="82" w="555" /><ent r="11" t="82" w="555" /><ent r="11" t="82" w="822" /><ent r="11" t="82" w="822" /><ent r="11" t="82" w="1076" /><ent r="11" t="82" w="1076" /><ent r="11" t="82" w="1284" /><ent r="11" t="82" w="1284" /><ent r="7" t="171" w="99" /><ent r="7" t="171" w="99" /><ent r="7" t="171" w="139" /><ent r="7" t="171" w="139" /><ent r="3" t="599" w="49" /><ent r="3" t="599" w="49" /><ent r="3" t="599" w="97" /><ent r="3" t="599" w="97" /><ent r="3" t="612" w="45" /><ent r="3" t="612" w="45" /></phr></stem><stem n="графиках"><phr n="графиках"><ent r="11" t="82" w="304" /><ent r="11" t="82" w="304" /><ent r="11" t="82" w="557" /><ent r="11" t="82" w="557" /><ent r="11" t="82" w="824" /><ent r="11" t="82" w="824" /><ent r="11" t="82" w="1078" /><ent r="11" t="82" w="1078" /><ent r="11" t="82" w="1286" /><ent r="11" t="82" w="1286" /></phr></stem><stem n="списках"><phr n="списках"><ent r="11" t="82" w="306" /><ent r="11" t="82" w="559" /><ent r="11" t="82" w="826" /><ent r="11" t="82" w="1080" /><ent r="11" t="82" w="1288" /><ent r="4" t="469" w="168" /></phr></stem><stem n="показатель"><phr n="Показатель"><ent r="12" t="82" w="308" /><ent r="12" t="82" w="308" /><ent r="12" t="82" w="561" /><ent r="12" t="82" w="561" /><ent r="12" t="82" w="828" /><ent r="12" t="82" w="828" /><ent r="12" t="82" w="1082" /><ent r="12" t="82" w="1082" /><ent r="12" t="82" w="1290" /><ent r="12" t="82" w="1290" /><ent r="1000" t="613" w="1" /><ent r="1000" t="613" w="1" /><ent r="102" t="613" w="4" /><ent r="102" t="613" w="4" /><ent r="3" t="613" w="7" /><ent r="3" t="613" w="7" /></phr><phr n="показатель"><ent r="65" t="582" w="89" /><ent r="65" t="582" w="89" /><ent r="3" t="582" w="115" /><ent r="3" t="582" w="115" /><ent r="6" t="586" w="98" /><ent r="6" t="586" w="98" /><ent r="4" t="612" w="88" /><ent r="4" t="612" w="88" /><ent r="4" t="612" w="122" /><ent r="4" t="612" w="122" /><ent r="3" t="613" w="26" /><ent r="3" t="613" w="26" /></phr></stem><stem n="диапазонные"><phr n="диапазонные"><ent r="11" t="82" w="320" /><ent r="11" t="82" w="320" /><ent r="11" t="82" w="573" /><ent r="11" t="82" w="573" /><ent r="11" t="82" w="840" /><ent r="11" t="82" w="840" /><ent r="11" t="82" w="1094" /><ent r="11" t="82" w="1094" /><ent r="11" t="82" w="1302" /><ent r="11" t="82" w="1302" /></phr></stem><stem n="показателей"><phr n="показателей"><ent r="11" t="82" w="329" /><ent r="11" t="82" w="582" /><ent r="11" t="82" w="849" /><ent r="11" t="82" w="1103" /><ent r="11" t="82" w="1311" /><ent r="3" t="85" w="40" /></phr></stem><stem n="системному"><phr n="системному"><ent r="15" t="82" w="348" /><ent r="15" t="82" w="348" /><ent r="15" t="82" w="601" /><ent r="15" t="82" w="601" /><ent r="15" t="82" w="868" /><ent r="15" t="82" w="868" /><ent r="15" t="82" w="1122" /><ent r="15" t="82" w="1122" /><ent r="15" t="82" w="1330" /><ent r="15" t="82" w="1330" /><ent r="6" t="146" w="225" /><ent r="6" t="146" w="225" /><ent r="3" t="175" w="81" /><ent r="3" t="175" w="81" /><ent r="3" t="362" w="38" /><ent r="3" t="362" w="38" /><ent r="6" t="664" w="175" /><ent r="6" t="664" w="175" /></phr></stem><stem n="разрез"><phr n="Разрез"><ent r="12" t="82" w="351" /><ent r="12" t="82" w="351" /><ent r="12" t="82" w="604" /><ent r="12" t="82" w="604" /><ent r="12" t="82" w="871" /><ent r="12" t="82" w="871" /><ent r="12" t="82" w="1125" /><ent r="12" t="82" w="1125" /><ent r="12" t="82" w="1333" /><ent r="12" t="82" w="1333" /><ent r="5" t="85" w="422" /><ent r="5" t="85" w="422" /><ent r="6" t="85" w="561" /><ent r="6" t="85" w="561" /></phr></stem><stem n="вычисления"><phr n="вычисления"><ent r="11" t="82" w="354" /><ent r="11" t="82" w="354" /><ent r="11" t="82" w="607" /><ent r="11" t="82" w="607" /><ent r="11" t="82" w="874" /><ent r="11" t="82" w="874" /><ent r="11" t="82" w="1128" /><ent r="11" t="82" w="1128" /><ent r="11" t="82" w="1336" /><ent r="11" t="82" w="1336" /><ent r="3" t="85" w="92" /><ent r="3" t="85" w="92" /><ent r="7" t="171" w="146" /><ent r="7" t="171" w="146" /><ent r="64" t="176" w="76" /><ent r="64" t="176" w="76" /><ent r="4" t="176" w="151" /><ent r="4" t="176" w="151" /><ent r="6" t="177" w="108" /><ent r="5" t="177" w="111" /><ent r="5" t="177" w="111" /><ent r="57" t="177" w="309" /><ent r="5" t="177" w="337" /><ent r="6" t="177" w="479" /><ent r="6" t="177" w="491" /><ent r="6" t="177" w="504" /><ent r="6" t="367" w="50" /><ent r="6" t="367" w="50" /><ent r="6" t="549" w="72" /><ent r="3" t="549" w="133" /><ent r="3" t="549" w="133" /><ent r="1000" t="598" w="2" /><ent r="1000" t="598" w="2" /><ent r="102" t="598" w="5" /><ent r="102" t="598" w="5" /><ent r="4" t="612" w="80" /><ent r="4" t="612" w="109" /><ent r="4" t="612" w="109" /><ent r="7" t="636" w="180" /><ent r="7" t="636" w="180" /></phr><phr n="Вычисления"><ent r="5" t="177" w="54" /><ent r="5" t="177" w="54" /><ent r="7" t="177" w="69" /><ent r="7" t="177" w="69" /><ent r="5" t="178" w="50" /><ent r="5" t="178" w="50" /><ent r="4" t="612" w="143" /></phr></stem><stem n="фактическая"><phr n="фактическая"><ent r="12" t="82" w="359" /><ent r="12" t="82" w="359" /><ent r="12" t="82" w="612" /><ent r="12" t="82" w="612" /><ent r="12" t="82" w="879" /><ent r="12" t="82" w="879" /><ent r="12" t="82" w="1133" /><ent r="12" t="82" w="1133" /><ent r="12" t="82" w="1341" /><ent r="12" t="82" w="1341" /></phr><phr n="Фактическая"><ent r="9" t="289" w="218" /><ent r="9" t="289" w="218" /><ent r="9" t="289" w="284" /><ent r="9" t="289" w="284" /><ent r="9" t="289" w="327" /><ent r="9" t="289" w="327" /><ent r="9" t="289" w="371" /><ent r="9" t="289" w="371" /><ent r="9" t="289" w="418" /><ent r="9" t="289" w="418" /><ent r="8" t="423" w="367" /><ent r="8" t="423" w="367" /><ent r="8" t="423" w="370" /><ent r="8" t="423" w="370" /><ent r="8" t="423" w="609" /><ent r="8" t="423" w="609" /><ent r="8" t="423" w="612" /><ent r="8" t="423" w="612" /><ent r="6" t="427" w="432" /><ent r="6" t="427" w="432" /><ent r="6" t="427" w="435" /><ent r="6" t="427" w="435" /><ent r="6" t="427" w="676" /><ent r="6" t="427" w="676" /><ent r="6" t="427" w="679" /><ent r="6" t="427" w="679" /><ent r="7" t="554" w="383" /><ent r="7" t="554" w="383" /><ent r="7" t="554" w="677" /><ent r="7" t="554" w="677" /></phr></stem><stem n="списочными"><phr n="списочными"><ent r="11" t="82" w="365" /><ent r="11" t="82" w="365" /><ent r="11" t="82" w="618" /><ent r="11" t="82" w="618" /><ent r="11" t="82" w="885" /><ent r="11" t="82" w="885" /><ent r="11" t="82" w="1139" /><ent r="11" t="82" w="1139" /><ent r="11" t="82" w="1347" /><ent r="11" t="82" w="1347" /></phr></stem><stem n="представлениями"><phr n="представлениями"><ent r="11" t="82" w="366" /><ent r="11" t="82" w="366" /><ent r="11" t="82" w="619" /><ent r="11" t="82" w="619" /><ent r="11" t="82" w="886" /><ent r="11" t="82" w="886" /><ent r="11" t="82" w="1140" /><ent r="11" t="82" w="1140" /><ent r="11" t="82" w="1348" /><ent r="11" t="82" w="1348" /></phr></stem><stem n="количественные"><phr n="количественные"><ent r="11" t="82" w="368" /><ent r="11" t="82" w="368" /><ent r="11" t="82" w="621" /><ent r="11" t="82" w="621" /><ent r="11" t="82" w="888" /><ent r="11" t="82" w="888" /><ent r="11" t="82" w="1142" /><ent r="11" t="82" w="1142" /><ent r="11" t="82" w="1350" /><ent r="11" t="82" w="1350" /></phr></stem><stem n="разрезы"><phr n="разрезы"><ent r="11" t="82" w="369" /><ent r="11" t="82" w="380" /><ent r="11" t="82" w="380" /><ent r="11" t="82" w="622" /><ent r="11" t="82" w="633" /><ent r="11" t="82" w="633" /><ent r="11" t="82" w="889" /><ent r="11" t="82" w="900" /><ent r="11" t="82" w="900" /><ent r="11" t="82" w="1143" /><ent r="11" t="82" w="1154" /><ent r="11" t="82" w="1154" /><ent r="11" t="82" w="1351" /><ent r="11" t="82" w="1362" /><ent r="11" t="82" w="1362" /><ent r="3" t="85" w="67" /></phr><phr n="Разрезы"><ent r="100" t="85" w="46" /><ent r="100" t="85" w="46" /><ent r="4" t="85" w="48" /><ent r="4" t="85" w="48" /></phr></stem><stem n="кол-во"><phr n="Кол-во"><ent r="11" t="82" w="371" /><ent r="11" t="82" w="371" /><ent r="11" t="82" w="624" /><ent r="11" t="82" w="624" /><ent r="11" t="82" w="891" /><ent r="11" t="82" w="891" /><ent r="11" t="82" w="1145" /><ent r="11" t="82" w="1145" /><ent r="11" t="82" w="1353" /><ent r="11" t="82" w="1353" /><ent r="9" t="289" w="767" /><ent r="9" t="289" w="767" /><ent r="5" t="468" w="129" /><ent r="5" t="468" w="129" /><ent r="5" t="468" w="139" /><ent r="5" t="468" w="139" /><ent r="5" t="468" w="160" /><ent r="5" t="468" w="160" /><ent r="5" t="512" w="138" /><ent r="5" t="512" w="138" /><ent r="5" t="512" w="148" /><ent r="5" t="512" w="148" /><ent r="6" t="513" w="185" /><ent r="6" t="513" w="185" /><ent r="6" t="660" w="119" /><ent r="6" t="660" w="119" /></phr><phr n="кол-во"><ent r="11" t="82" w="375" /><ent r="11" t="82" w="375" /><ent r="11" t="82" w="628" /><ent r="11" t="82" w="628" /><ent r="11" t="82" w="895" /><ent r="11" t="82" w="895" /><ent r="11" t="82" w="1149" /><ent r="11" t="82" w="1149" /><ent r="11" t="82" w="1357" /><ent r="11" t="82" w="1357" /><ent r="8" t="423" w="624" /><ent r="8" t="423" w="624" /><ent r="6" t="427" w="691" /><ent r="6" t="427" w="691" /><ent r="6" t="488" w="131" /><ent r="6" t="488" w="131" /></phr></stem><stem n="кол"><phr n="Кол"><ent r="11" t="82" w="371" /><ent r="11" t="82" w="624" /><ent r="11" t="82" w="891" /><ent r="11" t="82" w="1145" /><ent r="11" t="82" w="1353" /><ent r="9" t="289" w="767" /><ent r="5" t="468" w="129" /><ent r="5" t="468" w="139" /><ent r="5" t="468" w="160" /><ent r="5" t="512" w="138" /><ent r="5" t="512" w="148" /><ent r="6" t="513" w="185" /><ent r="6" t="660" w="119" /></phr><phr n="кол"><ent r="11" t="82" w="375" /><ent r="11" t="82" w="628" /><ent r="11" t="82" w="895" /><ent r="11" t="82" w="1149" /><ent r="11" t="82" w="1357" /><ent r="8" t="423" w="624" /><ent r="6" t="427" w="691" /><ent r="6" t="488" w="131" /><ent r="6" t="660" w="148" /></phr></stem><stem n="существуют"><phr n="Существуют"><ent r="11" t="82" w="378" /><ent r="11" t="82" w="378" /><ent r="11" t="82" w="631" /><ent r="11" t="82" w="631" /><ent r="11" t="82" w="898" /><ent r="11" t="82" w="898" /><ent r="11" t="82" w="1152" /><ent r="11" t="82" w="1152" /><ent r="11" t="82" w="1360" /><ent r="11" t="82" w="1360" /><ent r="3" t="85" w="19" /><ent r="3" t="85" w="19" /><ent r="3" t="198" w="671" /><ent r="3" t="198" w="671" /><ent r="3" t="381" w="26" /><ent r="3" t="381" w="26" /></phr><phr n="существуют"><ent r="56" t="145" w="367" /><ent r="56" t="145" w="367" /><ent r="3" t="173" w="68" /><ent r="3" t="173" w="68" /><ent r="5" t="359" w="112" /><ent r="5" t="359" w="112" /><ent r="3" t="422" w="74" /><ent r="3" t="422" w="74" /><ent r="9" t="425" w="174" /><ent r="9" t="425" w="174" /><ent r="6" t="456" w="81" /><ent r="6" t="456" w="81" /><ent r="3" t="460" w="46" /><ent r="3" t="460" w="46" /><ent r="6" t="460" w="78" /><ent r="6" t="460" w="78" /><ent r="3" t="463" w="27" /><ent r="3" t="463" w="27" /><ent r="6" t="463" w="63" /><ent r="6" t="463" w="63" /><ent r="6" t="475" w="50" /><ent r="6" t="475" w="50" /><ent r="6" t="479" w="69" /><ent r="6" t="479" w="69" /><ent r="4" t="505" w="658" /><ent r="4" t="505" w="658" /><ent r="3" t="620" w="50" /><ent r="3" t="620" w="50" /></phr></stem><stem n="ось-x"><phr n="Ось-X"><ent r="12" t="82" w="386" /><ent r="12" t="82" w="386" /><ent r="12" t="82" w="653" /><ent r="12" t="82" w="653" /><ent r="12" t="82" w="920" /><ent r="12" t="82" w="920" /></phr></stem><stem n="ось"><phr n="Ось"><ent r="12" t="82" w="386" /><ent r="12" t="82" w="399" /><ent r="12" t="82" w="653" /><ent r="12" t="82" w="666" /><ent r="12" t="82" w="920" /><ent r="12" t="82" w="933" /></phr></stem><stem n="x"><phr n="X"><ent r="12" t="82" w="387" /><ent r="11" t="82" w="396" /><ent r="11" t="82" w="396" /><ent r="12" t="82" w="654" /><ent r="11" t="82" w="663" /><ent r="11" t="82" w="663" /><ent r="12" t="82" w="921" /><ent r="11" t="82" w="930" /><ent r="11" t="82" w="930" /><ent r="57" t="85" w="232" /><ent r="57" t="85" w="232" /><ent r="57" t="85" w="243" /><ent r="57" t="85" w="277" /><ent r="57" t="85" w="277" /><ent r="4" t="217" w="71" /><ent r="4" t="217" w="71" /><ent r="4" t="217" w="91" /><ent r="4" t="217" w="91" /><ent r="6" t="221" w="88" /><ent r="6" t="221" w="88" /><ent r="6" t="221" w="141" /><ent r="6" t="221" w="141" /><ent r="6" t="221" w="207" /><ent r="6" t="221" w="207" /><ent r="6" t="229" w="89" /><ent r="6" t="229" w="89" /><ent r="6" t="229" w="130" /><ent r="6" t="229" w="130" /><ent r="6" t="231" w="88" /><ent r="6" t="231" w="88" /><ent r="6" t="231" w="181" /><ent r="6" t="231" w="181" /><ent r="6" t="359" w="713" /><ent r="6" t="359" w="713" /><ent r="6" t="359" w="724" /><ent r="6" t="636" w="320" /><ent r="6" t="663" w="187" /><ent r="6" t="663" w="187" /><ent r="6" t="663" w="205" /><ent r="6" t="663" w="205" /><ent r="6" t="663" w="318" /><ent r="6" t="663" w="318" /><ent r="6" t="663" w="338" /><ent r="6" t="663" w="338" /></phr><phr n="x"><ent r="4" t="557" w="216" /><ent r="4" t="557" w="216" /><ent r="6" t="580" w="68" /><ent r="6" t="580" w="68" /><ent r="6" t="586" w="79" /><ent r="6" t="586" w="79" /></phr></stem><stem n="метка"><phr n="Метка"><ent r="11" t="82" w="389" /><ent r="11" t="82" w="402" /><ent r="11" t="82" w="656" /><ent r="11" t="82" w="669" /><ent r="11" t="82" w="923" /><ent r="11" t="82" w="936" /><ent r="6" t="446" w="150" /><ent r="6" t="446" w="150" /></phr></stem><stem n="описания"><phr n="описания"><ent r="11" t="82" w="392" /><ent r="11" t="82" w="392" /><ent r="11" t="82" w="405" /><ent r="11" t="82" w="405" /><ent r="11" t="82" w="659" /><ent r="11" t="82" w="659" /><ent r="11" t="82" w="672" /><ent r="11" t="82" w="672" /><ent r="11" t="82" w="926" /><ent r="11" t="82" w="926" /><ent r="11" t="82" w="939" /><ent r="11" t="82" w="939" /><ent r="8" t="91" w="160" /><ent r="8" t="91" w="160" /><ent r="4" t="161" w="63" /><ent r="4" t="161" w="63" /><ent r="6" t="164" w="121" /><ent r="6" t="164" w="121" /><ent r="3" t="168" w="36" /><ent r="3" t="168" w="36" /><ent r="6" t="204" w="175" /><ent r="6" t="204" w="175" /><ent r="6" t="312" w="308" /><ent r="6" t="312" w="308" /><ent r="6" t="400" w="83" /><ent r="6" t="400" w="83" /><ent r="3" t="618" w="124" /><ent r="3" t="618" w="124" /><ent r="3" t="712" w="34" /><ent r="3" t="712" w="34" /></phr></stem><stem n="оси"><phr n="оси"><ent r="11" t="82" w="395" /><ent r="11" t="82" w="395" /><ent r="11" t="82" w="408" /><ent r="11" t="82" w="408" /><ent r="11" t="82" w="662" /><ent r="11" t="82" w="662" /><ent r="11" t="82" w="675" /><ent r="11" t="82" w="675" /><ent r="11" t="82" w="929" /><ent r="11" t="82" w="929" /><ent r="11" t="82" w="942" /><ent r="11" t="82" w="942" /><ent r="57" t="85" w="226" /><ent r="57" t="85" w="226" /><ent r="57" t="85" w="231" /><ent r="57" t="85" w="231" /><ent r="57" t="85" w="242" /><ent r="57" t="85" w="242" /><ent r="57" t="85" w="276" /><ent r="57" t="85" w="276" /><ent r="57" t="85" w="281" /><ent r="57" t="85" w="281" /><ent r="57" t="85" w="292" /><ent r="57" t="85" w="292" /><ent r="6" t="85" w="645" /><ent r="6" t="85" w="645" /><ent r="6" t="85" w="650" /><ent r="6" t="85" w="650" /></phr></stem></index>