<?xml version="1.0"?>
<method xmlns:xsi="http://www.w3.org/2001/XMLSchema-instance" xmlns:xsd="http://www.w3.org/2001/XMLSchema" id="9f29467f-b357-494b-81e9-408ba11b3515" lastModifiedUtc="2013-01-14T19:52:01.5140116Z" name="OnBeforeDelete" methodType="CrudEvent" actionType="None" returnMode="None">
  <extendedMetaData />
  <ExtendedPropertiesCollection>
    <extendee type="Sage.Platform.Orm.Entities.OrmEntityMethod" />
  </ExtendedPropertiesCollection>
  <parameter />
  <preExecuteTargets />
  <methodTargets>
    <methodTarget id="ba36593c-04ff-4992-913a-8f3f7eba4710" lastModifiedUtc="2013-01-14T19:52:00.5312242Z" targetType="Sage.Platform.Orm.DefaultCRUDEventHandler, Sage.Platform" targetMethod="OnBeforeDelete" active="true">
      <ExtendedPropertiesCollection>
        <extendee type="Sage.Platform.Orm.Entities.OrmMethodTarget" />
      </ExtendedPropertiesCollection>
    </methodTarget>
  </methodTargets>
  <postExecuteTargets />
  <postFlushTargets />
</method>