<?xml version="1.0"?>
<exportedFiles>
  <exportedFile url="\Portal\SlxClient\SupportFiles\images\InforSignIn\Company.png" timeStamp="2015-05-28T03:06:44.0000" />
  <exportedFile url="\Portal\SlxClient\SupportFiles\images\InforSignIn\Enivironment.png" timeStamp="2015-05-28T03:06:44.0000" />
  <exportedFile url="\Portal\SlxClient\SupportFiles\images\InforSignIn\Error.png" timeStamp="2015-05-28T03:06:44.0000" />
  <exportedFile url="\Portal\SlxClient\SupportFiles\images\InforSignIn\Language.png" timeStamp="2015-05-28T03:06:44.0000" />
  <exportedFile url="\Portal\SlxClient\SupportFiles\images\InforSignIn\logo.png" timeStamp="2015-05-28T03:06:44.0000" />
  <exportedFile url="\Portal\SlxClient\SupportFiles\images\InforSignIn\Ok.png" timeStamp="2015-05-28T03:06:44.0000" />
  <exportedFile url="\Portal\SlxClient\SupportFiles\images\InforSignIn\Password.png" timeStamp="2015-05-28T03:06:44.0000" />
  <exportedFile url="\Portal\SlxClient\SupportFiles\images\InforSignIn\Server.png" timeStamp="2015-05-28T03:06:44.0000" />
  <exportedFile url="\Portal\SlxClient\SupportFiles\images\InforSignIn\User.png" timeStamp="2015-05-28T03:06:44.0000" />
</exportedFiles>