<?xml version="1.0"?>
<exportedFiles>
  <exportedFile url="\Portal\SlxClient\ChildPages\InsertRole\InsertRole.page.xml" timeStamp="2015-05-28T03:05:11.0000" />
  <exportedFile url="\Portal\SlxClient\ChildPages\InsertRole\InsertRole.page.xml.de.resx" timeStamp="2015-05-28T03:05:11.0000" />
  <exportedFile url="\Portal\SlxClient\ChildPages\InsertRole\InsertRole.page.xml.fr.resx" timeStamp="2015-05-28T03:05:11.0000" />
  <exportedFile url="\Portal\SlxClient\ChildPages\InsertRole\InsertRole.page.xml.it.resx" timeStamp="2015-05-28T03:05:11.0000" />
  <exportedFile url="\Portal\SlxClient\ChildPages\InsertRole\InsertRole.page.xml.resx" timeStamp="2015-05-28T03:05:11.0000" />
  <exportedFile url="\Portal\SlxClient\ChildPages\InsertRole\InsertRole.page.xml.ru.resx" timeStamp="2015-05-28T03:05:11.0000" />
  <exportedFile url="\Portal\SlxClient\ChildPages\InsertRole\Modules.order.xml" timeStamp="2015-05-28T03:05:11.0000" />
  <exportedFile url="\Portal\SlxClient\ChildPages\InsertRole\SmartParts.order.xml" timeStamp="2015-05-28T03:05:11.0000" />
  <exportedFile url="\Portal\SlxClient\ChildPages\InsertRole\SmartParts\" />
</exportedFiles>