<?xml version="1.0"?>
<exportedFiles>
  <exportedFile url="\Entity Model\Relationships\Account.AccountOperatingCompany.af7d068319ff4bb89b80242dbb9bbf87.relationship.xml" timeStamp="2015-05-28T03:03:48.0000" />
  <exportedFile url="\Entity Model\Relationships\Account.AccountProduct.6f8874039d614a21b8bf58c93a4d70a5.relationship.xml" timeStamp="2015-05-28T03:03:48.0000" />
  <exportedFile url="\Entity Model\Relationships\Account.Address.477d405e1edb45b3a8ef076846dc3988.relationship.xml" timeStamp="2015-05-28T03:03:48.0000" />
  <exportedFile url="\Entity Model\Relationships\Account.Address.a6e41b881fab44f8b33d753230f30ef9.relationship.xml" timeStamp="2015-05-28T03:03:48.0000" />
  <exportedFile url="\Entity Model\Relationships\Account.Address.b1fbbad2d4e04de9810c0127b8d3cc4d.relationship.xml" timeStamp="2015-05-28T03:03:48.0000" />
  <exportedFile url="\Entity Model\Relationships\Account.AppIdMapping.fcf3d0e4051f4705a4cb264e08a4fb8b.relationship.xml" timeStamp="2015-05-28T03:03:48.0000" />
  <exportedFile url="\Entity Model\Relationships\Account.Contact.ea56bb1cb0b3421eb34c299ac26dabfd.relationship.xml" timeStamp="2015-05-28T03:03:48.0000" />
  <exportedFile url="\Entity Model\Relationships\Account.Contract.e8aee7eb73014ad498ebd6ce68c389e3.relationship.xml" timeStamp="2015-05-28T03:03:48.0000" />
  <exportedFile url="\Entity Model\Relationships\Account.ERPEmailAddress.a52c7a4e890f4afdb4f3c3051ed4f08d.relationship.xml" timeStamp="2015-05-28T03:03:48.0000" />
  <exportedFile url="\Entity Model\Relationships\Account.ERPPhoneNumber.5f9815ff13c0449d9a553b5b2897d133.relationship.xml" timeStamp="2015-05-28T03:03:48.0000" />
  <exportedFile url="\Entity Model\Relationships\Account.LeadSource.1c05cc84e3f34ec297ac4f3ef5992103.relationship.xml" timeStamp="2015-05-28T03:03:48.0000" />
  <exportedFile url="\Entity Model\Relationships\Account.Opportunity.0b050252b3a0453d91c2f33d86409e46.relationship.xml" timeStamp="2015-05-28T03:03:48.0000" />
  <exportedFile url="\Entity Model\Relationships\Account.Owner.6eea4e8cbada48fc9e4dcbda62fc527e.relationship.xml" timeStamp="2015-05-28T03:03:49.0000" />
  <exportedFile url="\Entity Model\Relationships\Account.Return.184bcc3b07a04caa8f5e7a81fccb9ea4.relationship.xml" timeStamp="2015-05-28T03:03:49.0000" />
  <exportedFile url="\Entity Model\Relationships\Account.SalesOrder.abecb883c002416e93bb2ac800d57e8a.relationship.xml" timeStamp="2015-05-28T03:03:49.0000" />
  <exportedFile url="\Entity Model\Relationships\Account.Ticket.beeaf5537b9242799abdb80a048ceea2.relationship.xml" timeStamp="2015-05-28T03:03:49.0000" />
  <exportedFile url="\Entity Model\Relationships\Account.User.03d231a10e13421e90726e2be6b19890.relationship.xml" timeStamp="2015-05-28T03:03:49.0000" />
  <exportedFile url="\Entity Model\Relationships\Account.User.f094a99e951746ffa3e12b55fc0197f2.relationship.xml" timeStamp="2015-05-28T03:03:49.0000" />
  <exportedFile url="\Entity Model\Relationships\Account.User.fa9b2ef253bb4a52be2b70e36b403672.relationship.xml" timeStamp="2015-05-28T03:03:49.0000" />
  <exportedFile url="\Entity Model\Relationships\AccountOperatingCompany.AppIdMapping.fa691d9f21c14484958935d4fdd94ca8.relationship.xml" timeStamp="2015-05-28T03:03:49.0000" />
  <exportedFile url="\Entity Model\Relationships\AccountProduct.Contact.b7c4074de8544d6aa5663e62dc28ca7e.relationship.xml" timeStamp="2015-05-28T03:03:49.0000" />
  <exportedFile url="\Entity Model\Relationships\AccountProduct.Opportunity.0982b4b9cc8d42b5a202cdbece2ab192.relationship.xml" timeStamp="2015-05-28T03:03:49.0000" />
  <exportedFile url="\Entity Model\Relationships\AccountProduct.Product.53b35602ba0e484ca710aa1b779c7eee.relationship.xml" timeStamp="2015-05-28T03:03:49.0000" />
  <exportedFile url="\Entity Model\Relationships\AccountProduct.Salesorder.ca6fad5572134d218399c79ece004cf1.relationship.xml" timeStamp="2015-05-28T03:03:49.0000" />
  <exportedFile url="\Entity Model\Relationships\AccountSummary.Owner.dc10eb0ee0304f4587ac60dbc15b23c7.relationship.xml" timeStamp="2015-05-28T03:03:49.0000" />
  <exportedFile url="\Entity Model\Relationships\AccountSyncView.Account.602739fac909427aaba8fbb93debcdc7.relationship.xml" timeStamp="2015-05-28T03:03:49.0000" />
  <exportedFile url="\Entity Model\Relationships\Activity.ActivityAttendee.9a7fc4f137604d93bedb1f53f6ecd551.relationship.xml" timeStamp="2015-05-28T03:03:49.0000" />
  <exportedFile url="\Entity Model\Relationships\Activity.AttendeeCountView.3318e630efdc4ba2b00767656876b43b.relationship.xml" timeStamp="2015-05-28T03:03:49.0000" />
  <exportedFile url="\Entity Model\Relationships\Activity.ResourceSchedule.5e3cd47e728f495086ad9684b8d45bbe.relationship.xml" timeStamp="2015-05-28T03:03:49.0000" />
  <exportedFile url="\Entity Model\Relationships\Activity.User.620ff522fa414577a8bf43c25a9dbbac.relationship.xml" timeStamp="2015-05-28T03:03:49.0000" />
  <exportedFile url="\Entity Model\Relationships\Activity.UserActivity.4ff009ca732f4a318fb4dd6d44ffa825.relationship.xml" timeStamp="2015-05-28T03:03:49.0000" />
  <exportedFile url="\Entity Model\Relationships\Activity.UserNotification.14031a8501344777a304444cf8130db0.relationship.xml" timeStamp="2015-05-28T03:03:49.0000" />
  <exportedFile url="\Entity Model\Relationships\ActivityTrackingEvent.ActivityTrackingEventExtract.b70428ed00744202ade2fd7de4b046cc.relationship.xml" timeStamp="2015-05-28T03:03:49.0000" />
  <exportedFile url="\Entity Model\Relationships\ActivityTrackingEvent.ActivityTrackingEvtAntn.7b5af107cf65406e8b74c9d9215cbbcd.relationship.xml" timeStamp="2015-05-28T03:03:49.0000" />
  <exportedFile url="\Entity Model\Relationships\Address.SalesOrderAddress.59825e3396f747d5ae4581bc05a80785.relationship.xml" timeStamp="2015-05-28T03:03:49.0000" />
  <exportedFile url="\Entity Model\Relationships\AppIdMapping.OAuthProvider.2d8e4a1285684a628429be118b69dd3f.relationship.xml" timeStamp="2015-05-28T03:03:49.0000" />
  <exportedFile url="\Entity Model\Relationships\AppIdMapping.SyncDigest.0a6196bf58d74de38fd01ac37c9cfe0f.relationship.xml" timeStamp="2015-05-28T03:03:49.0000" />
  <exportedFile url="\Entity Model\Relationships\AppIdMapping.SyncResult.9f00d8b721df4afdac8ccf0e8bfe37ea.relationship.xml" timeStamp="2015-05-28T03:03:49.0000" />
  <exportedFile url="\Entity Model\Relationships\AppIdMapping.SyncResult.fca5d54aa5874381a81422d12017866d.relationship.xml" timeStamp="2015-05-28T03:03:49.0000" />
  <exportedFile url="\Entity Model\Relationships\AppIdMapping.User.6a7fefe1cd1341838ed19c8091777de7.relationship.xml" timeStamp="2015-05-28T03:03:49.0000" />
  <exportedFile url="\Entity Model\Relationships\AppIdMapping.UserIntegrationMap.623fd3d198d142f78ef2bf13b880734e.relationship.xml" timeStamp="2015-05-28T03:03:49.0000" />
  <exportedFile url="\Entity Model\Relationships\AppIdMapping.UserIntegrationsView.1ea8a94e410f40bab2e2f19564daefd3.relationship.xml" timeStamp="2015-05-28T03:03:49.0000" />
  <exportedFile url="\Entity Model\Relationships\Association.Account.d3ac0f2674f347e298dbe86a8df8b9c2.relationship.xml" timeStamp="2015-05-28T03:03:49.0000" />
  <exportedFile url="\Entity Model\Relationships\Association.Account.df6a26854ad6421db0fc5d970b7cddeb.relationship.xml" timeStamp="2015-05-28T03:03:49.0000" />
  <exportedFile url="\Entity Model\Relationships\Association.Contact.21e002968f1744fa89a60cde74ae6b0f.relationship.xml" timeStamp="2015-05-28T03:03:49.0000" />
  <exportedFile url="\Entity Model\Relationships\Association.Contact.8fc9c6fc7ba647a69ace8fb5c1f27521.relationship.xml" timeStamp="2015-05-28T03:03:49.0000" />
  <exportedFile url="\Entity Model\Relationships\Attachment.RemoteAttachment.7bd2fdb998634ca0b8c7295e98e929fd.relationship.xml" timeStamp="2015-05-28T03:03:49.0000" />
  <exportedFile url="\Entity Model\Relationships\Attachment.User.d3873aafeccd419fbb1b2b54e7dd275b.relationship.xml" timeStamp="2015-05-28T03:03:49.0000" />
  <exportedFile url="\Entity Model\Relationships\CalendarHistorySyncView.History.dbc52d99c1ae41a8839612a0abce1237.relationship.xml" timeStamp="2015-05-28T03:03:49.0000" />
  <exportedFile url="\Entity Model\Relationships\CalendarSyncView.Activity.a834acf2f435422aa2d83bf1211fa051.relationship.xml" timeStamp="2015-05-28T03:03:49.0000" />
  <exportedFile url="\Entity Model\Relationships\Campaign.CampaignProduct.13c217a13e7149b0be246c2755d201d3.relationship.xml" timeStamp="2015-05-28T03:03:50.0000" />
  <exportedFile url="\Entity Model\Relationships\Campaign.CampaignStage.2ec0aa37bf30435d8f673a55336a2991.relationship.xml" timeStamp="2015-05-28T03:03:50.0000" />
  <exportedFile url="\Entity Model\Relationships\Campaign.CampaignTarget.d902c72fa37141f78cf0bcc0921c7bc4.relationship.xml" timeStamp="2015-05-28T03:03:50.0000" />
  <exportedFile url="\Entity Model\Relationships\Campaign.CampaignTask.18e99ff0cdff4a5eb58860a594228189.relationship.xml" timeStamp="2015-05-28T03:03:50.0000" />
  <exportedFile url="\Entity Model\Relationships\Campaign.OpportunityCampaign.28ca4e2e845b471d96bfb5640fb9de7e.relationship.xml" timeStamp="2015-05-28T03:03:50.0000" />
  <exportedFile url="\Entity Model\Relationships\Campaign.Owner.4a0d954e6e784b518fa6168d81edf061.relationship.xml" timeStamp="2015-05-28T03:03:50.0000" />
  <exportedFile url="\Entity Model\Relationships\Campaign.TargetResponse.c1770346c4f94a329741d92630f66777.relationship.xml" timeStamp="2015-05-28T03:03:50.0000" />
  <exportedFile url="\Entity Model\Relationships\Campaign.User.04f6aa3dd0b14e0f97b1225c2149a964.relationship.xml" timeStamp="2015-05-28T03:03:50.0000" />
  <exportedFile url="\Entity Model\Relationships\CampaignStage.CampaignTask.d8feeb65b5b94b879a53553fc538a986.relationship.xml" timeStamp="2015-05-28T03:03:50.0000" />
  <exportedFile url="\Entity Model\Relationships\CampaignStage.LeadSource.fcc82b14dbf4495688138223c79200e0.relationship.xml" timeStamp="2015-05-28T03:03:50.0000" />
  <exportedFile url="\Entity Model\Relationships\CampaignTarget.TargetResponse.80e3221fac984ce9b10ece0f71c4b529.relationship.xml" timeStamp="2015-05-28T03:03:50.0000" />
  <exportedFile url="\Entity Model\Relationships\CampaignTargetsView.Campaign.34aa639a55354b4fb709586ec61772f1.relationship.xml" timeStamp="2015-05-28T03:03:50.0000" />
  <exportedFile url="\Entity Model\Relationships\CampaignTargetsView.Owner.0089df5081934002a33c0572cafa3f2d.relationship.xml" timeStamp="2015-05-28T03:03:50.0000" />
  <exportedFile url="\Entity Model\Relationships\CommodityGroup.Product.f03a0a43d00243f0921fc3ca5d71184f.relationship.xml" timeStamp="2015-05-28T03:03:50.0000" />
  <exportedFile url="\Entity Model\Relationships\Competitor.Account.8a14af4872544ecdb43f0134bfa35b87.relationship.xml" timeStamp="2015-05-28T03:03:50.0000" />
  <exportedFile url="\Entity Model\Relationships\Competitor.OpportunityCompetitor.e9c27452f7dc4df49fe938c45d6472e2.relationship.xml" timeStamp="2015-05-28T03:03:50.0000" />
  <exportedFile url="\Entity Model\Relationships\Contact.Address.10d07a91bc6344a8a71ce4051c1e566c.relationship.xml" timeStamp="2015-05-28T03:03:50.0000" />
  <exportedFile url="\Entity Model\Relationships\Contact.Address.7576bb4cddd24e5bbd40a672ed0a0d7f.relationship.xml" timeStamp="2015-05-28T03:03:50.0000" />
  <exportedFile url="\Entity Model\Relationships\Contact.Address.d293b67e87c44fbbb59248584516bdfa.relationship.xml" timeStamp="2015-05-28T03:03:50.0000" />
  <exportedFile url="\Entity Model\Relationships\Contact.CampaignTarget.3717f28db1874f359e2e22514904dfa6.relationship.xml" timeStamp="2015-05-28T03:03:50.0000" />
  <exportedFile url="\Entity Model\Relationships\Contact.ContactAudit.01535a1d3e3f4a40848f74138dddf535.relationship.xml" timeStamp="2015-05-28T03:03:50.0000" />
  <exportedFile url="\Entity Model\Relationships\Contact.ContactLeadSource.b196513055f8414e98ec95f02466a1d0.relationship.xml" timeStamp="2015-05-28T03:03:50.0000" />
  <exportedFile url="\Entity Model\Relationships\Contact.ContactUser.791b61095fa745a28c59c11bca0dbcbf.relationship.xml" timeStamp="2015-05-28T03:03:50.0000" />
  <exportedFile url="\Entity Model\Relationships\Contact.Contract.bd05486615ec434e94886f4e99ecf539.relationship.xml" timeStamp="2015-05-28T03:03:50.0000" />
  <exportedFile url="\Entity Model\Relationships\Contact.ERPEmailAddress.e1959defb09a48518d856024a455e533.relationship.xml" timeStamp="2015-05-28T03:03:50.0000" />
  <exportedFile url="\Entity Model\Relationships\Contact.ERPPhoneNumber.f55dcc89e84f468195419c00ee5cd7ac.relationship.xml" timeStamp="2015-05-28T03:03:50.0000" />
  <exportedFile url="\Entity Model\Relationships\Contact.LitRequest.ddd263aeaac74511b26b2cada79147fa.relationship.xml" timeStamp="2015-05-28T03:03:50.0000" />
  <exportedFile url="\Entity Model\Relationships\Contact.OpportunityContact.d5d14f279b034bfaab9edaf871cd52aa.relationship.xml" timeStamp="2015-05-28T03:03:50.0000" />
  <exportedFile url="\Entity Model\Relationships\Contact.Owner.ba6e89fa60c14b958a0c44b25dfe0a06.relationship.xml" timeStamp="2015-05-28T03:03:50.0000" />
  <exportedFile url="\Entity Model\Relationships\Contact.Process.d8b4828627b143d283c21da3f3cf7448.relationship.xml" timeStamp="2015-05-28T03:03:50.0000" />
  <exportedFile url="\Entity Model\Relationships\Contact.SalesOrder.750fbda341294514862ea1d601836bed.relationship.xml" timeStamp="2015-05-28T03:03:50.0000" />
  <exportedFile url="\Entity Model\Relationships\Contact.TargetResponse.e471850788dc41eaae8595708fc87817.relationship.xml" timeStamp="2015-05-28T03:03:50.0000" />
  <exportedFile url="\Entity Model\Relationships\Contact.Ticket.fb3fdbf93aca4ad68fb1e3ea5a3e9029.relationship.xml" timeStamp="2015-05-28T03:03:50.0000" />
  <exportedFile url="\Entity Model\Relationships\Contact.User.8bab3e09b2564170a2901964dc7e268d.relationship.xml" timeStamp="2015-05-28T03:03:50.0000" />
  <exportedFile url="\Entity Model\Relationships\Contact.User.a5caa45b6e464fde9fc10c8c5487c9a6.relationship.xml" timeStamp="2015-05-28T03:03:50.0000" />
  <exportedFile url="\Entity Model\Relationships\Contact.User.db064fd5fb264b368723e0862a58320c.relationship.xml" timeStamp="2015-05-28T03:03:50.0000" />
  <exportedFile url="\Entity Model\Relationships\ContactSyncView.Contact.749b0ef15d7b45eabd261acf09063dce.relationship.xml" timeStamp="2015-05-28T03:03:50.0000" />
  <exportedFile url="\Entity Model\Relationships\Contract.ContractIncident.a65eb479d7ad4a6988a34e539c54b8ec.relationship.xml" timeStamp="2015-05-28T03:03:50.0000" />
  <exportedFile url="\Entity Model\Relationships\Contract.ContractItem.b24c8e73fb48465ba7675a4c8d7cbad7.relationship.xml" timeStamp="2015-05-28T03:03:50.0000" />
  <exportedFile url="\Entity Model\Relationships\Contract.Owner.edb399405dc0450e8b0f7ff1c47c5bdf.relationship.xml" timeStamp="2015-05-28T03:03:50.0000" />
  <exportedFile url="\Entity Model\Relationships\Contract.Ticket.625857612c3444ddbab90924564abb6a.relationship.xml" timeStamp="2015-05-28T03:03:50.0000" />
  <exportedFile url="\Entity Model\Relationships\ContractItem.AccountProduct.09233580eee04d9394e53930984898ab.relationship.xml" timeStamp="2015-05-28T03:03:50.0000" />
  <exportedFile url="\Entity Model\Relationships\DeDupJob.DeDupResult.bf0e35b5143b40089ea77ed301a890fa.relationship.xml" timeStamp="2015-05-28T03:03:50.0000" />
  <exportedFile url="\Entity Model\Relationships\DeDupResult.Owner.51d656a2640048379d22c79254c5fd65.relationship.xml" timeStamp="2015-05-28T03:03:50.0000" />
  <exportedFile url="\Entity Model\Relationships\Defect.DefectActivityItem.e368334fe2cf434bac0afcc980e5c1e2.relationship.xml" timeStamp="2015-05-28T03:03:50.0000" />
  <exportedFile url="\Entity Model\Relationships\Defect.DefectHistory.864150f11b2f4b8a90e970df3ac33b5f.relationship.xml" timeStamp="2015-05-28T03:03:50.0000" />
  <exportedFile url="\Entity Model\Relationships\Defect.DefectProduct.ddc75082f74547fdaca810bf03f666d1.relationship.xml" timeStamp="2015-05-28T03:03:50.0000" />
  <exportedFile url="\Entity Model\Relationships\Defect.DefectReturn.e52d9402d23340719a8e510d1795e0c0.relationship.xml" timeStamp="2015-05-28T03:03:50.0000" />
  <exportedFile url="\Entity Model\Relationships\Defect.DefectTicket.5fddce10962747379e3b4efadcf2ecbe.relationship.xml" timeStamp="2015-05-28T03:03:50.0000" />
  <exportedFile url="\Entity Model\Relationships\Defect.Owner.2163b2defc5d4b3a99f665030272e51c.relationship.xml" timeStamp="2015-05-28T03:03:50.0000" />
  <exportedFile url="\Entity Model\Relationships\Defect.Owner.ddaeca9ab2244bceaca87433a2dfcdb4.relationship.xml" timeStamp="2015-05-28T03:03:50.0000" />
  <exportedFile url="\Entity Model\Relationships\Defect.Owner.f6409527027e450283b54baba0d85733.relationship.xml" timeStamp="2015-05-28T03:03:50.0000" />
  <exportedFile url="\Entity Model\Relationships\Defect.Owner.f66b2b0baeb147c0a7597d5b5cd13825.relationship.xml" timeStamp="2015-05-28T03:03:50.0000" />
  <exportedFile url="\Entity Model\Relationships\DefectActivityItem.DefectActivityRate.52c48e9e42c444379ca5a13c1d2d9a7f.relationship.xml" timeStamp="2015-05-28T03:03:50.0000" />
  <exportedFile url="\Entity Model\Relationships\DefectActivityItem.User.e3a462fd115249078c046aa011835df1.relationship.xml" timeStamp="2015-05-28T03:03:50.0000" />
  <exportedFile url="\Entity Model\Relationships\DefectProduct.Product.f02ef26fe180488484d15c0396213018.relationship.xml" timeStamp="2015-05-28T03:03:50.0000" />
  <exportedFile url="\Entity Model\Relationships\Department.Owner.dbe244212f07401da64890b51c238279.relationship.xml" timeStamp="2015-05-28T03:03:50.0000" />
  <exportedFile url="\Entity Model\Relationships\ERPTradingAccount.Owner.b5919ab4f2d445ebbac999313a04644d.relationship.xml" timeStamp="2015-05-28T03:03:50.0000" />
  <exportedFile url="\Entity Model\Relationships\Event.User.84d8d9d307024d9cbc2b94b225d747ce.relationship.xml" timeStamp="2015-05-28T03:03:50.0000" />
  <exportedFile url="\Entity Model\Relationships\History.HistoryAttendee.1fd3eb1d22b94394bc45ad66fee88d25.relationship.xml" timeStamp="2015-05-28T03:03:50.0000" />
  <exportedFile url="\Entity Model\Relationships\ImportHistory.ImportHistoryItem.7b30ca733f67453cac1ec8b7c61057b3.relationship.xml" timeStamp="2015-05-28T03:03:50.0000" />
  <exportedFile url="\Entity Model\Relationships\ImportHistory.Owner.9d360c431e474a0e9671a2e0f8a44399.relationship.xml" timeStamp="2015-05-28T03:03:50.0000" />
  <exportedFile url="\Entity Model\Relationships\ImportTemplate.Owner.a615dbe817224240a76944d3523832ed.relationship.xml" timeStamp="2015-05-28T03:03:50.0000" />
  <exportedFile url="\Entity Model\Relationships\IndexDefinition.IndexSchedule.fc6302304f694b4087cf75e9713c6f81.relationship.xml" timeStamp="2015-05-28T03:03:50.0000" />
  <exportedFile url="\Entity Model\Relationships\Integration.AppIdMapping.15260719947a4fb4985b042b06106a82.relationship.xml" timeStamp="2015-05-28T03:03:50.0000" />
  <exportedFile url="\Entity Model\Relationships\Integration.IntegrationResource.13ed822bc13d4654ba6ac8a596e7c3b8.relationship.xml" timeStamp="2015-05-28T03:03:51.0000" />
  <exportedFile url="\Entity Model\Relationships\Integration.SyncJob.c4583b1efcaf4d4989287db0cf390688.relationship.xml" timeStamp="2015-05-28T03:03:51.0000" />
  <exportedFile url="\Entity Model\Relationships\Integration.UserIntegrationMap.10eb9bdd345e40dbb7af75827f69a9ec.relationship.xml" timeStamp="2015-05-28T03:03:51.0000" />
  <exportedFile url="\Entity Model\Relationships\Integration.UserIntegrationsView.772d0f1d8c464908aa9a6b18c6683175.relationship.xml" timeStamp="2015-05-28T03:03:51.0000" />
  <exportedFile url="\Entity Model\Relationships\Lead.CampaignTarget.4a6daf55b279485c8a5387a3f7f4623a.relationship.xml" timeStamp="2015-05-28T03:03:51.0000" />
  <exportedFile url="\Entity Model\Relationships\Lead.ERPEmailAddress.84c7718058ba41b38b08fff4dfc0b213.relationship.xml" timeStamp="2015-05-28T03:03:51.0000" />
  <exportedFile url="\Entity Model\Relationships\Lead.ERPPhoneNumber.bd1cd085aa214ee7889831063ff00594.relationship.xml" timeStamp="2015-05-28T03:03:51.0000" />
  <exportedFile url="\Entity Model\Relationships\Lead.LeadAddress.c097a72dd04a4c53be3ff1bc29362509.relationship.xml" timeStamp="2015-05-28T03:03:51.0000" />
  <exportedFile url="\Entity Model\Relationships\Lead.LeadAddress.fc87829494d543bc832ad484704b201d.relationship.xml" timeStamp="2015-05-28T03:03:51.0000" />
  <exportedFile url="\Entity Model\Relationships\Lead.LeadSource.4fa2aca4a61a4ff9ac8eaf5472e03bfe.relationship.xml" timeStamp="2015-05-28T03:03:51.0000" />
  <exportedFile url="\Entity Model\Relationships\Lead.Owner.2b1e4554b4e0458188b33c040d1b45a1.relationship.xml" timeStamp="2015-05-28T03:03:51.0000" />
  <exportedFile url="\Entity Model\Relationships\Lead.QualificationCategory.156348baa9574475a11043703308525c.relationship.xml" timeStamp="2015-05-28T03:03:51.0000" />
  <exportedFile url="\Entity Model\Relationships\Lead.TargetResponse.4e66a5759bee45b2b79a61a5eedaa575.relationship.xml" timeStamp="2015-05-28T03:03:51.0000" />
  <exportedFile url="\Entity Model\Relationships\Lead.User.de2b58942ab045c089158991297a9865.relationship.xml" timeStamp="2015-05-28T03:03:51.0000" />
  <exportedFile url="\Entity Model\Relationships\LeadAddressHistory.LeadHistory.edf76fac79e045f2802a6ed7d3506181.relationship.xml" timeStamp="2015-05-28T03:03:51.0000" />
  <exportedFile url="\Entity Model\Relationships\LeadHistory.LeadAddressHistory.2994d25c428a4489906351097992e446.relationship.xml" timeStamp="2015-05-28T03:03:51.0000" />
  <exportedFile url="\Entity Model\Relationships\LeadHistory.Owner.3f61bd3274f944d89831b37f096f1272.relationship.xml" timeStamp="2015-05-28T03:03:51.0000" />
  <exportedFile url="\Entity Model\Relationships\LeadImportMap.User.ec46086a5dc04229a02c3d35a77af4c8.relationship.xml" timeStamp="2015-05-28T03:03:51.0000" />
  <exportedFile url="\Entity Model\Relationships\LeadQualification.Lead.da89801699a74bd8b5d1984770f488a0.relationship.xml" timeStamp="2015-05-28T03:03:51.0000" />
  <exportedFile url="\Entity Model\Relationships\LeadQualification.Qualification.8538358630c74d0c80fce7235447d8aa.relationship.xml" timeStamp="2015-05-28T03:03:51.0000" />
  <exportedFile url="\Entity Model\Relationships\LeadSource.ContactLeadSource.c0f39d71fb44465fa9cc88c587870c30.relationship.xml" timeStamp="2015-05-28T03:03:51.0000" />
  <exportedFile url="\Entity Model\Relationships\LeadSyncView.Lead.9fb41c91e3464ac7bcc79007c6e13e27.relationship.xml" timeStamp="2015-05-28T03:03:51.0000" />
  <exportedFile url="\Entity Model\Relationships\LibraryDirs.LibraryDocs.e361225716414df48213589962e3aa09.relationship.xml" timeStamp="2015-05-28T03:03:51.0000" />
  <exportedFile url="\Entity Model\Relationships\LiteratureItem.LitRequestItem.521b7325c2ec44ef8c7f2092ff65e3b9.relationship.xml" timeStamp="2015-05-28T03:03:51.0000" />
  <exportedFile url="\Entity Model\Relationships\LitRequest.LitRequestItem.5cef9e9095314fde9b0dd005ad80168d.relationship.xml" timeStamp="2015-05-28T03:03:51.0000" />
  <exportedFile url="\Entity Model\Relationships\LitRequest.User.b1658b80eba346d1ade58ddeecd7b2ca.relationship.xml" timeStamp="2015-05-28T03:03:51.0000" />
  <exportedFile url="\Entity Model\Relationships\LitRequest.User.cb24770b3c944615b78fb5fcc9e9766e.relationship.xml" timeStamp="2015-05-28T03:03:51.0000" />
  <exportedFile url="\Entity Model\Relationships\MarketingServiceCampaign.Campaign.a3228127a9774703aeee82be85989b65.relationship.xml" timeStamp="2015-05-28T03:03:51.0000" />
  <exportedFile url="\Entity Model\Relationships\MarketingServiceCampaign.MarketingServiceRecipient.1019ce3a6845408aa6418a519027dd90.relationship.xml" timeStamp="2015-05-28T03:03:51.0000" />
  <exportedFile url="\Entity Model\Relationships\MarketingServiceRecipient.MarketingServiceClick.68ed4f2314d44053bc10830b3ec8de21.relationship.xml" timeStamp="2015-05-28T03:03:51.0000" />
  <exportedFile url="\Entity Model\Relationships\MarketingServiceRecipient.MarketingServiceOpen.31f2780627bd4267bd725bef74059aea.relationship.xml" timeStamp="2015-05-28T03:03:51.0000" />
  <exportedFile url="\Entity Model\Relationships\MarketingServiceRecipient.MarketingServiceUndeliverable.50495b8832054e7da328e2952023acc9.relationship.xml" timeStamp="2015-05-28T03:03:51.0000" />
  <exportedFile url="\Entity Model\Relationships\MarketingServiceUserInfo.User.50bdbc3226434bc99b7ad85282eeec9d.relationship.xml" timeStamp="2015-05-28T03:03:51.0000" />
  <exportedFile url="\Entity Model\Relationships\OAuthProvider.Integration.ecd33230640949b5b576d7e2fcfca84e.relationship.xml" timeStamp="2015-05-28T03:03:51.0000" />
  <exportedFile url="\Entity Model\Relationships\OAuthProvider.OAuthProviderScope.f725f179d2404872adb85d186c66ddf0.relationship.xml" timeStamp="2015-05-28T03:03:51.0000" />
  <exportedFile url="\Entity Model\Relationships\OAuthProvider.UserOAuthToken.ee58c9867e784aefaa9723c3190d9449.relationship.xml" timeStamp="2015-05-28T03:03:51.0000" />
  <exportedFile url="\Entity Model\Relationships\Opportunity.Account.1b0ae472e330478cb61e4209e5eb69d1.relationship.xml" timeStamp="2015-05-28T03:03:51.0000" />
  <exportedFile url="\Entity Model\Relationships\Opportunity.AppIdMapping.51c81448d5c449f682e01df636013d74.relationship.xml" timeStamp="2015-05-28T03:03:51.0000" />
  <exportedFile url="\Entity Model\Relationships\Opportunity.LeadSource.6e30ba9e02d54bfaba85593818d905a6.relationship.xml" timeStamp="2015-05-28T03:03:51.0000" />
  <exportedFile url="\Entity Model\Relationships\Opportunity.OpportunityCampaign.ae74252d65114c6cb833e8fab7779699.relationship.xml" timeStamp="2015-05-28T03:03:51.0000" />
  <exportedFile url="\Entity Model\Relationships\Opportunity.OpportunityCompetitor.94ee93a637b54bb8a68b6e2320ad09d3.relationship.xml" timeStamp="2015-05-28T03:03:51.0000" />
  <exportedFile url="\Entity Model\Relationships\Opportunity.OpportunityContact.ad5ae0c71d6a46449a6fe3e51048772d.relationship.xml" timeStamp="2015-05-28T03:03:51.0000" />
  <exportedFile url="\Entity Model\Relationships\Opportunity.OpportunityProduct.90d94880d0e340869a606338cc293708.relationship.xml" timeStamp="2015-05-28T03:03:51.0000" />
  <exportedFile url="\Entity Model\Relationships\Opportunity.Owner.9be9544a1278435a9ce2330818ca6ef9.relationship.xml" timeStamp="2015-05-28T03:03:51.0000" />
  <exportedFile url="\Entity Model\Relationships\Opportunity.Salesorder.d7e817e0672e414cad4e577532dc7ea1.relationship.xml" timeStamp="2015-05-28T03:03:51.0000" />
  <exportedFile url="\Entity Model\Relationships\Opportunity.SlxPriceList.530bee82232e4bb0bb3830f3288d4a5e.relationship.xml" timeStamp="2015-05-28T03:03:51.0000" />
  <exportedFile url="\Entity Model\Relationships\Opportunity.User.779261975e7d41719d9ae3c0405c32bd.relationship.xml" timeStamp="2015-05-28T03:03:51.0000" />
  <exportedFile url="\Entity Model\Relationships\Opportunity.User.a080ed44912c46d6beb5e480c3fbdd65.relationship.xml" timeStamp="2015-05-28T03:03:51.0000" />
  <exportedFile url="\Entity Model\Relationships\Opportunity.User.df253243ba7c49509e6aee8c45bcd6fa.relationship.xml" timeStamp="2015-05-28T03:03:51.0000" />
  <exportedFile url="\Entity Model\Relationships\OpportunityContact.Competitor.90d3f5c75eb346b7ad443192f91c81f6.relationship.xml" timeStamp="2015-05-28T03:03:51.0000" />
  <exportedFile url="\Entity Model\Relationships\Owner.Account.d61c1c9189f44baa83d7cfc02e81572e.relationship.xml" timeStamp="2015-05-28T03:03:51.0000" />
  <exportedFile url="\Entity Model\Relationships\Owner.CustomSetting.fe55b3abc09044dd80c2a5c8995473f3.relationship.xml" timeStamp="2015-05-28T03:03:51.0000" />
  <exportedFile url="\Entity Model\Relationships\Owner.OwnerJoin.0b89f026b6b64ee1a5dd515cda9a6d30.relationship.xml" timeStamp="2015-05-28T03:03:51.0000" />
  <exportedFile url="\Entity Model\Relationships\Owner.OwnerJoin.c11408d6fda047c7a8919b61e86cb610.relationship.xml" timeStamp="2015-05-28T03:03:51.0000" />
  <exportedFile url="\Entity Model\Relationships\Owner.OwnerRights.ca0a5b6b8193404fa75411859d102f1a.relationship.xml" timeStamp="2015-05-28T03:03:51.0000" />
  <exportedFile url="\Entity Model\Relationships\Owner.OwnerView.fd5f0a6c488f406bac291668640447a8.relationship.xml" timeStamp="2015-05-28T03:03:51.0000" />
  <exportedFile url="\Entity Model\Relationships\Owner.ReportFilter.b59131769ce946d6a093ec6b0e5444e9.relationship.xml" timeStamp="2015-05-28T03:03:52.0000" />
  <exportedFile url="\Entity Model\Relationships\OwnerJoin.OwnerSecurityProfile.907235dd48884bca956c5c087ab0dbe9.relationship.xml" timeStamp="2015-05-28T03:03:52.0000" />
  <exportedFile url="\Entity Model\Relationships\OwnerRights.OwnerSecurityProfile.ae4200085328458bbaa6245440ae207b.relationship.xml" timeStamp="2015-05-28T03:03:52.0000" />
  <exportedFile url="\Entity Model\Relationships\OwnerRights.User.d72a27c6e5754d008690ec282dd4b780.relationship.xml" timeStamp="2015-05-28T03:03:52.0000" />
  <exportedFile url="\Entity Model\Relationships\Package.PackageProduct.321fa158eed742a5894a8cd81282d1e1.relationship.xml" timeStamp="2015-05-28T03:03:52.0000" />
  <exportedFile url="\Entity Model\Relationships\PackageProduct.Product.5367d0f408424806ae40fd581be598ec.relationship.xml" timeStamp="2015-05-28T03:03:52.0000" />
  <exportedFile url="\Entity Model\Relationships\PicklistView.PicklistItemView.fdb3e1b57f034e6999b64e72f7bd0d48.relationship.xml" timeStamp="2015-05-28T03:03:52.0000" />
  <exportedFile url="\Entity Model\Relationships\Process.Activity.04d09f081d924dcfbdfcb900806e1701.relationship.xml" timeStamp="2015-05-28T03:03:52.0000" />
  <exportedFile url="\Entity Model\Relationships\Process.User.477384045a2e4dc59ae4deee7c521a70.relationship.xml" timeStamp="2015-05-28T03:03:52.0000" />
  <exportedFile url="\Entity Model\Relationships\Process.User.98d2fc25fd3646738fa470f3ac13b428.relationship.xml" timeStamp="2015-05-28T03:03:52.0000" />
  <exportedFile url="\Entity Model\Relationships\ProcessInstanceStatus.ActivityTrackingEvent.f50bb2cb12ef4297810799faf64e7802.relationship.xml" timeStamp="2015-05-28T03:03:52.0000" />
  <exportedFile url="\Entity Model\Relationships\ProcessInstanceStatus.ProcessTrackingEvent.fa33074e99b843a680b3e831ff69e914.relationship.xml" timeStamp="2015-05-28T03:03:52.0000" />
  <exportedFile url="\Entity Model\Relationships\ProcessInstanceStatus.ProcessTypeInformation.6d12a2e8acbc4790bddf602ffa7981d7.relationship.xml" timeStamp="2015-05-28T03:03:52.0000" />
  <exportedFile url="\Entity Model\Relationships\ProcessInstanceStatus.UserTrackingEvent.0b646949cf4d4dee994453be3534dd51.relationship.xml" timeStamp="2015-05-28T03:03:52.0000" />
  <exportedFile url="\Entity Model\Relationships\ProcessTrackingEvent.ProcessTrackingEventAnnotation.e3dd900083a543ef8599ee37508173d9.relationship.xml" timeStamp="2015-05-28T03:03:52.0000" />
  <exportedFile url="\Entity Model\Relationships\ProcessTypeInformation.ProcessTypeCategory.04834569b36f4b739aa630eabefa2914.relationship.xml" timeStamp="2015-05-28T03:03:52.0000" />
  <exportedFile url="\Entity Model\Relationships\ProdPackageKitView.PackageKitChildView.127f4e1c50db43c88f4a67ea7ce5413f.relationship.xml" timeStamp="2015-05-28T03:03:52.0000" />
  <exportedFile url="\Entity Model\Relationships\Product.CampaignProduct.19ebd637c4ba420fa0957fef2c4fd387.relationship.xml" timeStamp="2015-05-28T03:03:52.0000" />
  <exportedFile url="\Entity Model\Relationships\Product.OpportunityProduct.10b268b5e4374c42930ab6e848838b14.relationship.xml" timeStamp="2015-05-28T03:03:52.0000" />
  <exportedFile url="\Entity Model\Relationships\Product.PackageProduct.e225fd75dced441fbda3357fc2708d31.relationship.xml" timeStamp="2015-05-28T03:03:52.0000" />
  <exportedFile url="\Entity Model\Relationships\Product.ProductProgram.ff1e26b6c74f4999aff08b42df3257b8.relationship.xml" timeStamp="2015-05-28T03:03:52.0000" />
  <exportedFile url="\Entity Model\Relationships\Product.SalesOrderItem.02abd3f61cfd4245a2fa54b7cceccc52.relationship.xml" timeStamp="2015-05-28T03:03:52.0000" />
  <exportedFile url="\Entity Model\Relationships\Product.SlxPrice.22a25bcdd3ac498bae3f0b6c3274cfed.relationship.xml" timeStamp="2015-05-28T03:03:52.0000" />
  <exportedFile url="\Entity Model\Relationships\Product.UnitOfMeasure.5f5a89342b7e4ad88be1ff19b3d20bce.relationship.xml" timeStamp="2015-05-28T03:03:52.0000" />
  <exportedFile url="\Entity Model\Relationships\Product.UnitOfMeasure.91536d0bc23642a5838bb2887142d0f2.relationship.xml" timeStamp="2015-05-28T03:03:52.0000" />
  <exportedFile url="\Entity Model\Relationships\QualificationCategory.Qualification.5d55f27ef0b346a494b776e5530eb7b7.relationship.xml" timeStamp="2015-05-28T03:03:52.0000" />
  <exportedFile url="\Entity Model\Relationships\ReportHistory.History.9d1459fceb2747acada1dd1d4878fa58.relationship.xml" timeStamp="2015-05-28T03:03:52.0000" />
  <exportedFile url="\Entity Model\Relationships\ReportHistory.Owner.f3ecba57eec949959da86c3e347519bb.relationship.xml" timeStamp="2015-05-28T03:03:52.0000" />
  <exportedFile url="\Entity Model\Relationships\ReportHistory.User.2cbf0a112c9f4572838e1462b3194aab.relationship.xml" timeStamp="2015-05-28T03:03:52.0000" />
  <exportedFile url="\Entity Model\Relationships\ReportHistory.User.f9403c08fd77427da2c958c6846c40f7.relationship.xml" timeStamp="2015-05-28T03:03:52.0000" />
  <exportedFile url="\Entity Model\Relationships\ResourceList.ResourceSchedule.7afa6a3aec64448b975d7997ac233ba4.relationship.xml" timeStamp="2015-05-28T03:03:52.0000" />
  <exportedFile url="\Entity Model\Relationships\ResponseProduct.Product.1e3fa54dd40541ae8787bca9f793490f.relationship.xml" timeStamp="2015-05-28T03:03:52.0000" />
  <exportedFile url="\Entity Model\Relationships\Return.Contact.58f0524fb7cf48969bdb13564f8a610f.relationship.xml" timeStamp="2015-05-28T03:03:52.0000" />
  <exportedFile url="\Entity Model\Relationships\Return.Contact.7e7990681e4146e28d98cdf901f98bd5.relationship.xml" timeStamp="2015-05-28T03:03:52.0000" />
  <exportedFile url="\Entity Model\Relationships\Return.DefectReturn.098d48b8365349b6821f7a7060273205.relationship.xml" timeStamp="2015-05-28T03:03:52.0000" />
  <exportedFile url="\Entity Model\Relationships\Return.Owner.04c7b6936d164bf08e35043de640b432.relationship.xml" timeStamp="2015-05-28T03:03:52.0000" />
  <exportedFile url="\Entity Model\Relationships\Return.Owner.3215ec6810c642a29c3d908ac0c85010.relationship.xml" timeStamp="2015-05-28T03:03:52.0000" />
  <exportedFile url="\Entity Model\Relationships\Return.Owner.3513ed62971e4d9c8f5e00303c6c5ea7.relationship.xml" timeStamp="2015-05-28T03:03:52.0000" />
  <exportedFile url="\Entity Model\Relationships\Return.Owner.bba788c87408403aa7fe727bb2c30c89.relationship.xml" timeStamp="2015-05-28T03:03:52.0000" />
  <exportedFile url="\Entity Model\Relationships\Return.ReturnAddress.afbcce9f1547423eb19efab348357f30.relationship.xml" timeStamp="2015-05-28T03:03:52.0000" />
  <exportedFile url="\Entity Model\Relationships\Return.ReturnAddress.dede2a903a204aec84041db5057ccc97.relationship.xml" timeStamp="2015-05-28T03:03:52.0000" />
  <exportedFile url="\Entity Model\Relationships\Return.ReturnReceivedProduct.bde564f76b9842229a4951c48c6df495.relationship.xml" timeStamp="2015-05-28T03:03:52.0000" />
  <exportedFile url="\Entity Model\Relationships\Return.ReturnShippedProduct.b67acfcade434e6fab1834b872f95801.relationship.xml" timeStamp="2015-05-28T03:03:52.0000" />
  <exportedFile url="\Entity Model\Relationships\ReturnReceivedProduct.AccountProduct.02cb7f93fac44eb7888b08db90aadc31.relationship.xml" timeStamp="2015-05-28T03:03:52.0000" />
  <exportedFile url="\Entity Model\Relationships\ReturnReceivedProduct.User.1c52e9af4cc047a092a2ea6c7bf61fc5.relationship.xml" timeStamp="2015-05-28T03:03:52.0000" />
  <exportedFile url="\Entity Model\Relationships\ReturnShippedProduct.AccountProduct.812d36364e3f40a4938200739b0e074b.relationship.xml" timeStamp="2015-05-28T03:03:52.0000" />
  <exportedFile url="\Entity Model\Relationships\ReturnShippedProduct.Product.8a961f2e0f574c5a94a5a9842009fe8b.relationship.xml" timeStamp="2015-05-28T03:03:52.0000" />
  <exportedFile url="\Entity Model\Relationships\ReturnShippedProduct.ReturnReceivedProduct.ffc96b099195450b9cac5d8c75db0f98.relationship.xml" timeStamp="2015-05-28T03:03:52.0000" />
  <exportedFile url="\Entity Model\Relationships\ReturnShippedProduct.User.8060ec5f357548d1b8992d80328b8ca9.relationship.xml" timeStamp="2015-05-28T03:03:52.0000" />
  <exportedFile url="\Entity Model\Relationships\Role.SecuredActionRole.79c31ebca0404ccebbf9448e8108b930.relationship.xml" timeStamp="2015-05-28T03:03:52.0000" />
  <exportedFile url="\Entity Model\Relationships\Role.UserRole.0e495d4cac354d029984d60e83d41200.relationship.xml" timeStamp="2015-05-28T03:03:53.0000" />
  <exportedFile url="\Entity Model\Relationships\SalesOrder.AppIdMapping.00b159de0584473fa4ba6a1f88b3c8b7.relationship.xml" timeStamp="2015-05-28T03:03:53.0000" />
  <exportedFile url="\Entity Model\Relationships\Salesorder.Contact.2f69f4279cdc4ee9be2c0f2d9580a3e3.relationship.xml" timeStamp="2015-05-28T03:03:53.0000" />
  <exportedFile url="\Entity Model\Relationships\Salesorder.Contact.569fc7a8e5044cb6a3247ac152635c47.relationship.xml" timeStamp="2015-05-28T03:03:53.0000" />
  <exportedFile url="\Entity Model\Relationships\SalesOrder.Owner.13200822be024f2492f74a229612cecf.relationship.xml" timeStamp="2015-05-28T03:03:53.0000" />
  <exportedFile url="\Entity Model\Relationships\SalesOrder.SalesOrderAddress.0070c24f7693413ba46a0bf451db2c88.relationship.xml" timeStamp="2015-05-28T03:03:53.0000" />
  <exportedFile url="\Entity Model\Relationships\SalesOrder.SalesOrderAddress.29b49d41c9e14eb0a351dfcd2af1b312.relationship.xml" timeStamp="2015-05-28T03:03:53.0000" />
  <exportedFile url="\Entity Model\Relationships\SalesOrder.SalesOrderAddress.2df4fb4b481e43b8b044922682fabb09.relationship.xml" timeStamp="2015-05-28T03:03:53.0000" />
  <exportedFile url="\Entity Model\Relationships\SalesOrder.SalesOrderItem.d6aa2394bcc547a39de460f1a6134b84.relationship.xml" timeStamp="2015-05-28T03:03:53.0000" />
  <exportedFile url="\Entity Model\Relationships\SalesOrder.SlxPriceList.90859f5e33e8472eba7a3a05e5328a95.relationship.xml" timeStamp="2015-05-28T03:03:53.0000" />
  <exportedFile url="\Entity Model\Relationships\SalesOrder.User.e52a3f367d1b4ed191e2d4f1f1a6d7d2.relationship.xml" timeStamp="2015-05-28T03:03:53.0000" />
  <exportedFile url="\Entity Model\Relationships\SalesOrderItem.OpportunityProduct.e592a97aa2ea472a8729be80dc5648d8.relationship.xml" timeStamp="2015-05-28T03:03:53.0000" />
  <exportedFile url="\Entity Model\Relationships\SalesOrderItem.SlxLocation.d038baceb9684b80b01f9d43271e490b.relationship.xml" timeStamp="2015-05-28T03:03:53.0000" />
  <exportedFile url="\Entity Model\Relationships\SalesOrderItem.UnitOfMeasure.00accf868767435ea0a191ea9a0e4e55.relationship.xml" timeStamp="2015-05-28T03:03:53.0000" />
  <exportedFile url="\Entity Model\Relationships\SalesOrderSyncView.SalesOrder.aa78f6d4045949f98c75ff548be37738.relationship.xml" timeStamp="2015-05-28T03:03:53.0000" />
  <exportedFile url="\Entity Model\Relationships\SalesProcesses.SalesProcessAudit.441e728f8b9d485eb9d74f6134ce43e1.relationship.xml" timeStamp="2015-05-28T03:03:53.0000" />
  <exportedFile url="\Entity Model\Relationships\SalesQuotationSyncView.SalesOrder.2102fa07140b46e99e070d0c07a6209c.relationship.xml" timeStamp="2015-05-28T03:03:53.0000" />
  <exportedFile url="\Entity Model\Relationships\SecuredAction.SecuredActionRole.15ae5e8b65604a8e9fe9e71a1a08ad2b.relationship.xml" timeStamp="2015-05-28T03:03:53.0000" />
  <exportedFile url="\Entity Model\Relationships\SlxPrice.UnitOfMeasure.b580636c0f704d69924fb760ec484464.relationship.xml" timeStamp="2015-05-28T03:03:53.0000" />
  <exportedFile url="\Entity Model\Relationships\SlxPriceList.SlxPrice.63b7e2a39b024c728b819327340f503c.relationship.xml" timeStamp="2015-05-28T03:03:53.0000" />
  <exportedFile url="\Entity Model\Relationships\SyncJob.SlxLogItem.fbd6c023bd534a2c9c2ea35d7f99a7ae.relationship.xml" timeStamp="2015-05-28T03:03:53.0000" />
  <exportedFile url="\Entity Model\Relationships\SyncJob.SyncResult.494e8233762943bc9575c9ad35571589.relationship.xml" timeStamp="2015-05-28T03:03:53.0000" />
  <exportedFile url="\Entity Model\Relationships\SyncResult.Owner.26d4a89661f740e7adb6de8614ee45c0.relationship.xml" timeStamp="2015-05-28T03:03:53.0000" />
  <exportedFile url="\Entity Model\Relationships\SyncResult.User.36eecf1ff94548428a6383d7b3157303.relationship.xml" timeStamp="2015-05-28T03:03:53.0000" />
  <exportedFile url="\Entity Model\Relationships\SyncStatus.SyncResult.ad2fa53805a948b0aab4006e57289b86.relationship.xml" timeStamp="2015-05-28T03:03:53.0000" />
  <exportedFile url="\Entity Model\Relationships\TargetResponse.MarketingServiceRecipient.1fb4c3fbbea0482db8d3f9cc9d421420.relationship.xml" timeStamp="2015-05-28T03:03:53.0000" />
  <exportedFile url="\Entity Model\Relationships\TargetResponse.ResponseProduct.1bbad109b1464eb2beb0879a29b547ae.relationship.xml" timeStamp="2015-05-28T03:03:53.0000" />
  <exportedFile url="\Entity Model\Relationships\TaskSyncView.Activity.26d5cac07ee74358966b341d8ffbf4e9.relationship.xml" timeStamp="2015-05-28T03:03:53.0000" />
  <exportedFile url="\Entity Model\Relationships\TaskSyncView.History.b49ca8fc63d04d9da707ac729fddadfd.relationship.xml" timeStamp="2015-05-28T03:03:53.0000" />
  <exportedFile url="\Entity Model\Relationships\Team.Owner.a7a96fd2d75d4b349697354f36af0c2a.relationship.xml" timeStamp="2015-05-28T03:03:53.0000" />
  <exportedFile url="\Entity Model\Relationships\Ticket.ContractIncident.b69a0c3e31cd4cc99b6e1bca14f57dd0.relationship.xml" timeStamp="2015-05-28T03:03:53.0000" />
  <exportedFile url="\Entity Model\Relationships\Ticket.DefectTicket.6d9664b2d5d94450a78c3585bd4d55fa.relationship.xml" timeStamp="2015-05-28T03:03:53.0000" />
  <exportedFile url="\Entity Model\Relationships\Ticket.Owner.2b61dc2c3490438cad8a23954c1c48f8.relationship.xml" timeStamp="2015-05-28T03:03:53.0000" />
  <exportedFile url="\Entity Model\Relationships\Ticket.Owner.4ade667b57664af0833c88afd0ae8437.relationship.xml" timeStamp="2015-05-28T03:03:53.0000" />
  <exportedFile url="\Entity Model\Relationships\Ticket.Owner.9aafd81f97954fcb81e550d49100c620.relationship.xml" timeStamp="2015-05-28T03:03:53.0000" />
  <exportedFile url="\Entity Model\Relationships\Ticket.Owner.9ed909cae93f4ccb94795bf4a71441be.relationship.xml" timeStamp="2015-05-28T03:03:53.0000" />
  <exportedFile url="\Entity Model\Relationships\Ticket.Return.e1de465595a94845980994e037e77dce.relationship.xml" timeStamp="2015-05-28T03:03:53.0000" />
  <exportedFile url="\Entity Model\Relationships\Ticket.TicketAccountProduct.1c7763eb6bbc47829a844edcbd787df9.relationship.xml" timeStamp="2015-05-28T03:03:53.0000" />
  <exportedFile url="\Entity Model\Relationships\Ticket.TicketActivity.180278788fbb421e9a4292b7283c466b.relationship.xml" timeStamp="2015-05-28T03:03:53.0000" />
  <exportedFile url="\Entity Model\Relationships\Ticket.TicketHistory.4495f6b6862f493c8f9cf192273807a5.relationship.xml" timeStamp="2015-05-28T03:03:53.0000" />
  <exportedFile url="\Entity Model\Relationships\Ticket.Urgency.75a607cd28d047bb8e5de7679bfd46fe.relationship.xml" timeStamp="2015-05-28T03:03:53.0000" />
  <exportedFile url="\Entity Model\Relationships\TicketAccountProduct.AccountProduct.a59bcc7d690341a2af0de6a74983612f.relationship.xml" timeStamp="2015-05-28T03:03:53.0000" />
  <exportedFile url="\Entity Model\Relationships\TicketActivity.ContractIncident.e17d14c7ef0643b596022506c4448aba.relationship.xml" timeStamp="2015-05-28T03:03:53.0000" />
  <exportedFile url="\Entity Model\Relationships\TicketActivity.TicketActivityItem.0af818edd4ce40ad9885e9654d8dac06.relationship.xml" timeStamp="2015-05-28T03:03:53.0000" />
  <exportedFile url="\Entity Model\Relationships\TicketActivity.TicketActivityRate.7ba0894d49734220b7114021bb8c7ded.relationship.xml" timeStamp="2015-05-28T03:03:53.0000" />
  <exportedFile url="\Entity Model\Relationships\TicketActivity.User.7944164128cd4d54a5dc7ff31c5584ef.relationship.xml" timeStamp="2015-05-28T03:03:53.0000" />
  <exportedFile url="\Entity Model\Relationships\TicketActivityItem.AccountProduct.930bb018d3bc42b08eb2c40ddf95a88a.relationship.xml" timeStamp="2015-05-28T03:03:53.0000" />
  <exportedFile url="\Entity Model\Relationships\TicketActivityItem.Product.c3b7d602c3a04a41a2f474ad1a358be4.relationship.xml" timeStamp="2015-05-28T03:03:53.0000" />
  <exportedFile url="\Entity Model\Relationships\TicketAreaOwner.Owner.65b8070b71784647808ef07d94597a86.relationship.xml" timeStamp="2015-05-28T03:03:53.0000" />
  <exportedFile url="\Entity Model\Relationships\TicketProblemType.TicketProblemSolutionType.02fed71984c74394ad232f0134043f88.relationship.xml" timeStamp="2015-05-28T03:03:53.0000" />
  <exportedFile url="\Entity Model\Relationships\TicketSolutionType.TicketProblemSolutionType.87e92255efba46968f9362c8f432b4c5.relationship.xml" timeStamp="2015-05-28T03:03:53.0000" />
  <exportedFile url="\Entity Model\Relationships\User.ContactUser.23cc3dccd9c74e4bbac4f947d82a4582.relationship.xml" timeStamp="2015-05-28T03:03:53.0000" />
  <exportedFile url="\Entity Model\Relationships\User.Owner.14a709f41ba948c68c8bdb72681569d3.relationship.xml" timeStamp="2015-05-28T03:03:53.0000" />
  <exportedFile url="\Entity Model\Relationships\User.ResourceList.bc65ab5b22364e09b1f6832c1d04cb89.relationship.xml" timeStamp="2015-05-28T03:03:53.0000" />
  <exportedFile url="\Entity Model\Relationships\User.UserAudit.d6ecd6136fdd4ca7b41a28b31a5f7185.relationship.xml" timeStamp="2015-05-28T03:03:53.0000" />
  <exportedFile url="\Entity Model\Relationships\User.UserCalendar.066395632ace4951942d7130b087567b.relationship.xml" timeStamp="2015-05-28T03:03:53.0000" />
  <exportedFile url="\Entity Model\Relationships\User.UserCalendar.6c422b5a06c342eab85dd773138ffeec.relationship.xml" timeStamp="2015-05-28T03:03:53.0000" />
  <exportedFile url="\Entity Model\Relationships\User.UserIntegrationMap.4abc6661e01d41d0ba225eaf564ff25a.relationship.xml" timeStamp="2015-05-28T03:03:53.0000" />
  <exportedFile url="\Entity Model\Relationships\User.UserIntegrationsView.3907aee9e4f24eaa8fade0f38b2fc8cc.relationship.xml" timeStamp="2015-05-28T03:03:53.0000" />
  <exportedFile url="\Entity Model\Relationships\User.UserRole.2cfdb4ccefed46648f232c76835c3261.relationship.xml" timeStamp="2015-05-28T03:03:53.0000" />
  <exportedFile url="\Entity Model\Relationships\UserActivity.User.6a42694200174057ad939e17763bacab.relationship.xml" timeStamp="2015-05-28T03:03:53.0000" />
  <exportedFile url="\Entity Model\Relationships\UserInfo.Address.070b0c31131e45f3a5e25318c262320a.relationship.xml" timeStamp="2015-05-28T03:03:53.0000" />
  <exportedFile url="\Entity Model\Relationships\UserInfo.Address.2b44b615e79c49d6bc0a38d0b8bcda49.relationship.xml" timeStamp="2015-05-28T03:03:53.0000" />
  <exportedFile url="\Entity Model\Relationships\UserInfo.Address.f74761a81a84468c80d262763e23ccec.relationship.xml" timeStamp="2015-05-28T03:03:53.0000" />
  <exportedFile url="\Entity Model\Relationships\UserNotification.User.1c8c9fa3327d413fa71ec8ed729c8006.relationship.xml" timeStamp="2015-05-28T03:03:53.0000" />
  <exportedFile url="\Entity Model\Relationships\UserNotification.User.2049ea31d0fa452b9a5f610faa083bba.relationship.xml" timeStamp="2015-05-28T03:03:53.0000" />
  <exportedFile url="\Entity Model\Relationships\UserOAuthToken.AppIdMapping.1235bd4697954c1c85cb14736c16615f.relationship.xml" timeStamp="2015-05-28T03:03:53.0000" />
  <exportedFile url="\Entity Model\Relationships\UserOAuthToken.User.9adf65b6c8614dc0b8a1c9f7a183f78f.relationship.xml" timeStamp="2015-05-28T03:03:53.0000" />
  <exportedFile url="\Entity Model\Relationships\UserSubscription.User.29468d69cd7f4d1b934a9b18bad783af.relationship.xml" timeStamp="2015-05-28T03:03:53.0000" />
  <exportedFile url="\Entity Model\Relationships\UserTrackingEvent.UserTrackingEventAnnotation.92798a14ccf04492a6b0bda29cf0cfd8.relationship.xml" timeStamp="2015-05-28T03:03:53.0000" />
  <exportedFile url="\Entity Model\Relationships\UserTrackingEvent.UserTrackingEvtExt.c867bcd02f6f4055b92be7000781c84c.relationship.xml" timeStamp="2015-05-28T03:03:54.0000" />
</exportedFiles>