<?xml version="1.0"?>
<exportedFiles>
  <exportedFile url="\Portal\SLXCustomerPortal\SupportFiles\help\fr\WebCustomerPortal.htm" timeStamp="2015-05-28T02:51:19.0000" />
  <exportedFile url="\Portal\SLXCustomerPortal\SupportFiles\help\fr\WebCustomerPortal.js" timeStamp="2015-05-28T02:51:19.0000" />
  <exportedFile url="\Portal\SLXCustomerPortal\SupportFiles\help\fr\WebCustomerPortal.mcwebhelp" timeStamp="2015-05-28T02:51:19.0000" />
  <exportedFile url="\Portal\SLXCustomerPortal\SupportFiles\help\fr\WebCustomerPortal_CSH.htm" timeStamp="2015-05-28T02:51:19.0000" />
  <exportedFile url="\Portal\SLXCustomerPortal\SupportFiles\help\fr\WebCustomerPortal_Left.htm" timeStamp="2015-05-28T02:51:19.0000" />
  <exportedFile url="\Portal\SLXCustomerPortal\SupportFiles\help\fr\Content\" />
  <exportedFile url="\Portal\SLXCustomerPortal\SupportFiles\help\fr\Data\" />
  <exportedFile url="\Portal\SLXCustomerPortal\SupportFiles\help\fr\Skin\" />
</exportedFiles>